{success:true,deathRecords:[{"deceasedName":"POONAM SHARMA","yearOfregistration":"2014","dateOfRegistration":"","deathRegnNo":"9133","deathDate":"","crematoriumName":"C.M.H.O. SPL. REGISTRATION","deceasedSex":"FEMALE","crematoriumCode":"","fatherName":".................N/M...............","regnNo":"","deathSite":"DESUN HOSPITAL AND HEART INSTITUTE,KOLKATA 700107"},{"deceasedName":"AHLAD MOYEE KUTI","yearOfregistration":"2014","dateOfRegistration":"","deathRegnNo":"6679","deathDate":"","crematoriumName":"N.E.C.(T)","deceasedSex":"FEMALE","crematoriumCode":"","fatherName":"N/M","regnNo":"","deathSite":""},{"deceasedName":"KRISHNA CHANDRA GHOSH","yearOfregistration":"2014","dateOfRegistration":"","deathRegnNo":"1690","deathDate":"","crematoriumName":"SIRITY B. GHAT E. (T)","deceasedSex":"MALE","crematoriumCode":"","fatherName":"LATE ALIK MOHAN GHOSH","regnNo":"","deathSite":"RABINDRANATH TAGORE INTERNATIONAL INSTITUTE OF CARDIAC SCIENCES,KOLKATA-99"},{"deceasedName":"SARASWATI BISWAS","yearOfregistration":"2014","dateOfRegistration":"","deathRegnNo":"10310","deathDate":"","crematoriumName":"M.G.E.C.(T)","deceasedSex":"FEMALE","crematoriumCode":"","fatherName":"N/A","regnNo":"","deathSite":"R K M SEVA PRATISHTHAN.  KOL-26"},{"deceasedName":"MD.PARVEZ","yearOfregistration":"2014","dateOfRegistration":"","deathRegnNo":"1356","deathDate":"","crematoriumName":"GOBRA B.G(T)","deceasedSex":"MALE","crematoriumCode":"","fatherName":"ABDUL RAHMAN","regnNo":"","deathSite":""},{"deceasedName":"HEM CHANDRA PAL","yearOfregistration":"2014","dateOfRegistration":"","deathRegnNo":"10300","deathDate":"","crematoriumName":"M.G.E.C.(T)","deceasedSex":"MALE","crematoriumCode":"","fatherName":"LATE SADHAN CHANDRA PAL","regnNo":"","deathSite":""},{"deceasedName":"NIRMAL SINGH","yearOfregistration":"2014","dateOfRegistration":"","deathRegnNo":"97","deathDate":"","crematoriumName":"BIRJUNALA E.C. (T)","deceasedSex":"MALE","crematoriumCode":"","fatherName":"LT. BHUSALY SINGH","regnNo":"","deathSite":""},{"deceasedName":"RAVI MONDAL","yearOfregistration":"2014","dateOfRegistration":"","deathRegnNo":"10304","deathDate":"","crematoriumName":"M.G.E.C.(T)","deceasedSex":"MALE","crematoriumCode":"","fatherName":"LATE NISHI KANTA MONDAL","regnNo":"","deathSite":"AROGYA MATERNITY AND NURSING HOME"},{"deceasedName":"DEBENDRANATH DAS","yearOfregistration":"2014","dateOfRegistration":"","deathRegnNo":"1693","deathDate":"","crematoriumName":"SIRITY B. GHAT E. (T)","deceasedSex":"MALE","crematoriumCode":"","fatherName":"LATE BISWAMBHAR DAS","regnNo":"","deathSite":"DESUN HOSPITAL AND HEART INSTITUTE,KOLKATA 700107"},{"deceasedName":"LOKNATH HAZRA","yearOfregistration":"2014","dateOfRegistration":"","deathRegnNo":"6685","deathDate":"","crematoriumName":"N.E.C.(T)","deceasedSex":"MALE","crematoriumCode":"","fatherName":"LATE BANAMALI HAZRA","regnNo":"","deathSite":""},{"deceasedName":"GANESH CHANDRA GHATAK","yearOfregistration":"2014","dateOfRegistration":"","deathRegnNo":"1893","deathDate":"","crematoriumName":"C.B.G.(T)","deceasedSex":"MALE","crematoriumCode":"","fatherName":"LATE HARAN CHANDRA GHATAK","regnNo":"","deathSite":"APOLLO GLENEAGLES HOSPITAL KOL-54"},{"deceasedName":"B/O RUMPA PAL","yearOfregistration":"2014","dateOfRegistration":"","deathRegnNo":"780","deathDate":"","crematoriumName":"TOPSIA HINDU B.G.(T)","deceasedSex":"MALE","crematoriumCode":"","fatherName":"PRITHWIRAJ PAL","regnNo":"","deathSite":"BHAGIRATHI NEOTIA WOMEN AND CHILD CARE CENTRE"},{"deceasedName":"MONMOHAN SINGH","yearOfregistration":"2014","dateOfRegistration":"","deathRegnNo":"1697","deathDate":"","crematoriumName":"SIRITY B. GHAT E. (T)","deceasedSex":"MALE","crematoriumCode":"","fatherName":"LT.RANJOTH SINGH","regnNo":"","deathSite":"M R BANGUR HOSPITAL,KOLKATA 700033"},{"deceasedName":"MOTI LAL SHAW","yearOfregistration":"2014","dateOfRegistration":"","deathRegnNo":"6702","deathDate":"","crematoriumName":"N.E.C.(T)","deceasedSex":"MALE","crematoriumCode":"","fatherName":"LATE RUP NARAYAN SHAW","regnNo":"","deathSite":"SHREE VISHUDHANAND HOSP AND R. INSTITUTE KOL"},{"deceasedName":"KALYANI CHAKRABORTY","yearOfregistration":"2014","dateOfRegistration":"","deathRegnNo":"10327","deathDate":"","crematoriumName":"M.G.E.C.(T)","deceasedSex":"FEMALE","crematoriumCode":"","fatherName":"N/A","regnNo":"","deathSite":""},{"deceasedName":"RAM PRAKASH SARAF","yearOfregistration":"2014","dateOfRegistration":"","deathRegnNo":"1083","deathDate":"","crematoriumName":"N.B.G.(T)","deceasedSex":"MALE","crematoriumCode":"","fatherName":"LATE BAL MUKUND SARAF","regnNo":"","deathSite":""},{"deceasedName":"BABY SARMA","yearOfregistration":"2014","dateOfRegistration":"","deathRegnNo":"10322","deathDate":"","crematoriumName":"M.G.E.C.(T)","deceasedSex":"FEMALE","crematoriumCode":"","fatherName":"N/A","regnNo":"","deathSite":""},{"deceasedName":"SK.SAFIUDDIN","yearOfregistration":"2014","dateOfRegistration":"","deathRegnNo":"1361","deathDate":"","crematoriumName":"GOBRA B.G(T)","deceasedSex":"MALE","crematoriumCode":"","fatherName":"S/O- LATE SK.SADEK","regnNo":"","deathSite":""},{"deceasedName":"KAMESWAR CHOWDHURY","yearOfregistration":"2014","dateOfRegistration":"","deathRegnNo":"6713","deathDate":"","crematoriumName":"N.E.C.(T)","deceasedSex":"MALE","crematoriumCode":"","fatherName":"S/O LT. JAGADISH CHOWDHURY","regnNo":"","deathSite":"E.S.I. HOSPITAL,MANICKTALA,KOLKATA-54"},{"deceasedName":"UTTAM KUMAR SHAW","yearOfregistration":"2014","dateOfRegistration":"","deathRegnNo":"1086","deathDate":"","crematoriumName":"N.B.G.(T)","deceasedSex":"MALE","crematoriumCode":"","fatherName":"S/O LATE DUKHI PRASAD SHAW","regnNo":"","deathSite":""},{"deceasedName":"SAKALDIP ROY","yearOfregistration":"2014","dateOfRegistration":"","deathRegnNo":"9358","deathDate":"","crematoriumName":"C.M.H.O. SPL. REGISTRATION","deceasedSex":"MALE","crematoriumCode":"","fatherName":"BUJHAWAN ROY","regnNo":"","deathSite":"COMMAND HOSPITAL (E.C.) KOL"},{"deceasedName":"ARATI NAG CHOWDHURY","yearOfregistration":"2014","dateOfRegistration":"","deathRegnNo":"1692","deathDate":"","crematoriumName":"SIRITY B. GHAT E. (T)","deceasedSex":"FEMALE","crematoriumCode":"","fatherName":"N/M","regnNo":"","deathSite":"M R BANGUR HOSPITAL,KOLKATA 700033"},{"deceasedName":"PIU KUMARI","yearOfregistration":"2014","dateOfRegistration":"","deathRegnNo":"784","deathDate":"","crematoriumName":"TOPSIA HINDU B.G.(T)","deceasedSex":"FEMALE","crematoriumCode":"","fatherName":"LAXMAN GORAI","regnNo":"","deathSite":"S S K M HOSPITAL. KOLKATA"},{"deceasedName":"ASIT KABI","yearOfregistration":"2014","dateOfRegistration":"","deathRegnNo":"10305","deathDate":"","crematoriumName":"M.G.E.C.(T)","deceasedSex":"MALE","crematoriumCode":"","fatherName":"LATE RANJIT KABI","regnNo":"","deathSite":"APOLLO GLENEAGLES HOSPITAL KOL-54"},{"deceasedName":"SUDARSAN RAY","yearOfregistration":"2014","dateOfRegistration":"","deathRegnNo":"10569","deathDate":"","crematoriumName":"C.M.H.O. SPL. REGISTRATION","deceasedSex":"MALE","crematoriumCode":"","fatherName":"LATE KANAI LAL ROY","regnNo":"","deathSite":"S S K M HOSPITAL. KOLKATA"},{"deceasedName":"SARASWATI SARKAR","yearOfregistration":"2014","dateOfRegistration":"","deathRegnNo":"962","deathDate":"","crematoriumName":"K.M.B.G.(T)","deceasedSex":"FEMALE","crematoriumCode":"","fatherName":"X","regnNo":"","deathSite":"N R S MEDICAL COLLEGE AND HOSPITAL. KOLKATA-14"},{"deceasedName":"MINATI MUKHERJEE","yearOfregistration":"2014","dateOfRegistration":"","deathRegnNo":"1872","deathDate":"","crematoriumName":"GARIA B.G.(T)","deceasedSex":"FEMALE","crematoriumCode":"","fatherName":"N/M","regnNo":"","deathSite":""},{"deceasedName":"PARBOTI MAHAPATRA","yearOfregistration":"2014","dateOfRegistration":"","deathRegnNo":"10313","deathDate":"","crematoriumName":"M.G.E.C.(T)","deceasedSex":"FEMALE","crematoriumCode":"","fatherName":"N/A","regnNo":"","deathSite":"S S K M HOSPITAL. KOLKATA"},{"deceasedName":"BACHHU JAISWAL","yearOfregistration":"2014","dateOfRegistration":"","deathRegnNo":"10314","deathDate":"","crematoriumName":"M.G.E.C.(T)","deceasedSex":"MALE","crematoriumCode":"","fatherName":"LATE BISWANATH JAISWAL","regnNo":"","deathSite":"M R BANGUR HOSPITAL,KOLKATA 700033"},{"deceasedName":"SRIDAM MONDAL","yearOfregistration":"2014","dateOfRegistration":"","deathRegnNo":"6701","deathDate":"","crematoriumName":"N.E.C.(T)","deceasedSex":"MALE","crematoriumCode":"","fatherName":"LATE PRANNATH MONDAL","regnNo":"","deathSite":""},{"deceasedName":"SOUMYADEEP HAZRA","yearOfregistration":"2014","dateOfRegistration":"","deathRegnNo":"781","deathDate":"","crematoriumName":"TOPSIA HINDU B.G.(T)","deceasedSex":"MALE","crematoriumCode":"","fatherName":"BIRENDRANATH HAZRA","regnNo":"","deathSite":"CHITTARANJAN SEBA SADAN & SISHU SADAN"},{"deceasedName":"SASANKA SEKHAR MANNA","yearOfregistration":"2014","dateOfRegistration":"","deathRegnNo":"10667","deathDate":"","crematoriumName":"C.M.H.O. SPL. REGISTRATION","deceasedSex":"MALE","crematoriumCode":"","fatherName":"LATE HARIHAR MANNA","regnNo":"","deathSite":"S S K M HOSPITAL. KOLKATA"},{"deceasedName":"TARA MONI SONKAR","yearOfregistration":"2014","dateOfRegistration":"","deathRegnNo":"1081","deathDate":"","crematoriumName":"N.B.G.(T)","deceasedSex":"FEMALE","crematoriumCode":"","fatherName":"N/M","regnNo":"","deathSite":""},{"deceasedName":"CHANDRA SEKHAR GUPTA","yearOfregistration":"2014","dateOfRegistration":"","deathRegnNo":"6699","deathDate":"","crematoriumName":"N.E.C.(T)","deceasedSex":"MALE","crematoriumCode":"","fatherName":"TARAK NATH GUPTA","regnNo":"","deathSite":"R G KAR MEDICAL COLLEGE AND HOSPITAL KOL"},{"deceasedName":"RAM CHANDRA BISWAKARMA","yearOfregistration":"2014","dateOfRegistration":"","deathRegnNo":"6709","deathDate":"","crematoriumName":"N.E.C.(T)","deceasedSex":"MALE","crematoriumCode":"","fatherName":"S/O LATE BISHRAMJI","regnNo":"","deathSite":""},{"deceasedName":"ASHARANI SARKAR","yearOfregistration":"2014","dateOfRegistration":"","deathRegnNo":"10303","deathDate":"","crematoriumName":"M.G.E.C.(T)","deceasedSex":"FEMALE","crematoriumCode":"","fatherName":"N/A","regnNo":"","deathSite":""},{"deceasedName":"HALIMAN BIBI","yearOfregistration":"2014","dateOfRegistration":"","deathRegnNo":"404","deathDate":"","crematoriumName":"BAGMARI B.G. (T)","deceasedSex":"FEMALE","crematoriumCode":"","fatherName":"--------N/M--------","regnNo":"","deathSite":""},{"deceasedName":"AMRITA KUMAR DEY","yearOfregistration":"2014","dateOfRegistration":"","deathRegnNo":"10318","deathDate":"","crematoriumName":"C.M.H.O. SPL. REGISTRATION","deceasedSex":"MALE","crematoriumCode":"","fatherName":"LATE KHIROD KUMAR DEY","regnNo":"","deathSite":"KPC MEDICAL COLLEGE AND HOSPITAL,JADAVPUR"},{"deceasedName":"KHATIZA KHATOON","yearOfregistration":"2014","dateOfRegistration":"","deathRegnNo":"1362","deathDate":"","crematoriumName":"GOBRA B.G(T)","deceasedSex":"FEMALE","crematoriumCode":"","fatherName":"--------N/M--------","regnNo":"","deathSite":""},{"deceasedName":"ROHIT SARDAR","yearOfregistration":"2014","dateOfRegistration":"","deathRegnNo":"410","deathDate":"","crematoriumName":"MURARIPUKUR B.G. (T)","deceasedSex":"MALE","crematoriumCode":"","fatherName":"PALASH SARDAR","regnNo":"","deathSite":"S S K M HOSPITAL. KOLKATA"},{"deceasedName":"ANITA AGARWAL","yearOfregistration":"2014","dateOfRegistration":"","deathRegnNo":"1085","deathDate":"","crematoriumName":"N.B.G.(T)","deceasedSex":"FEMALE","crematoriumCode":"","fatherName":"N/M","regnNo":"","deathSite":""},{"deceasedName":"MRINAL MANDAL","yearOfregistration":"2014","dateOfRegistration":"","deathRegnNo":"1881","deathDate":"","crematoriumName":"GARIA B.G.(T)","deceasedSex":"MALE","crematoriumCode":"","fatherName":"KIYANANDA MANDAL","regnNo":"","deathSite":"M R BANGUR HOSPITAL,KOLKATA 700033"},{"deceasedName":"FALGUNI GANGOPADHYAY","yearOfregistration":"2014","dateOfRegistration":"","deathRegnNo":"10372","deathDate":"","crematoriumName":"M.G.E.C.(T)","deceasedSex":"FEMALE","crematoriumCode":"","fatherName":"N/A","regnNo":"","deathSite":"JAMES LONG CLINIC (P) LTD"},{"deceasedName":"GOPAL CH. JANA","yearOfregistration":"2014","dateOfRegistration":"","deathRegnNo":"9558","deathDate":"","crematoriumName":"C.M.H.O. SPL. REGISTRATION","deceasedSex":"MALE","crematoriumCode":"","fatherName":"PANCHANAN JANA","regnNo":"","deathSite":"N R S MEDICAL COLLEGE AND HOSPITAL. KOLKATA-14"},{"deceasedName":"JHARNA BASU","yearOfregistration":"2014","dateOfRegistration":"","deathRegnNo":"1869","deathDate":"","crematoriumName":"GARIA B.G.(T)","deceasedSex":"FEMALE","crematoriumCode":"","fatherName":"N/M","regnNo":"","deathSite":"PEERLESS HOSPITEX HOSPITAL AND RESEARCH CENTER LIMITED, KOLKATA-94."},{"deceasedName":"SAMARENDRA NATH SAHA","yearOfregistration":"2014","dateOfRegistration":"","deathRegnNo":"10788","deathDate":"","crematoriumName":"C.M.H.O. SPL. REGISTRATION","deceasedSex":"MALE","crematoriumCode":"","fatherName":"LATE SITANATH SAHA","regnNo":"","deathSite":""},{"deceasedName":"BANKIM SAMANTA","yearOfregistration":"2014","dateOfRegistration":"","deathRegnNo":"9612","deathDate":"","crematoriumName":"C.M.H.O. SPL. REGISTRATION","deceasedSex":"MALE","crematoriumCode":"","fatherName":"LATE CHAITANYA SAMANTA","regnNo":"","deathSite":"PEERLESS HOSPITEX HOSPITAL AND RESEARCH CENTER LIMITED, KOLKATA-94."},{"deceasedName":"SK. ABBASH ALI","yearOfregistration":"2014","dateOfRegistration":"","deathRegnNo":"11315","deathDate":"","crematoriumName":"C.M.H.O. SPL. REGISTRATION","deceasedSex":"MALE","crematoriumCode":"","fatherName":"LATE SK. AHAMADI","regnNo":"","deathSite":"S S K M HOSPITAL. KOLKATA"},{"deceasedName":"SANKAR GAYEN","yearOfregistration":"2014","dateOfRegistration":"","deathRegnNo":"10903","deathDate":"","crematoriumName":"C.M.H.O. SPL. REGISTRATION","deceasedSex":"MALE","crematoriumCode":"","fatherName":"KASHINATH GAYEN","regnNo":"","deathSite":"S S K M HOSPITAL. KOLKATA"},{"deceasedName":"TARAK NATH DUTTA","yearOfregistration":"2014","dateOfRegistration":"","deathRegnNo":"6693","deathDate":"","crematoriumName":"N.E.C.(T)","deceasedSex":"MALE","crematoriumCode":"","fatherName":"LATE LAKSHMI KANTO DUTTA","regnNo":"","deathSite":"B.R.SINGH HOSPITAL,KOLKATA"},{"deceasedName":"MD KALLAM","yearOfregistration":"2014","dateOfRegistration":"","deathRegnNo":"407","deathDate":"","crematoriumName":"BAGMARI B.G. (T)","deceasedSex":"MALE","crematoriumCode":"","fatherName":"LATE KALLU","regnNo":"","deathSite":""},{"deceasedName":"SHILU DIPA","yearOfregistration":"2014","dateOfRegistration":"","deathRegnNo":"10336","deathDate":"","crematoriumName":"M.G.E.C.(T)","deceasedSex":"FEMALE","crematoriumCode":"","fatherName":"N/A","regnNo":"","deathSite":"GAMMA CENTAURI HEALTH CARE P.LTD."},{"deceasedName":"NIRANJAN DAS","yearOfregistration":"2014","dateOfRegistration":"","deathRegnNo":"10309","deathDate":"","crematoriumName":"M.G.E.C.(T)","deceasedSex":"MALE","crematoriumCode":"","fatherName":"N/A","regnNo":"","deathSite":"SAROJ GUPTA CANCER CENTRE & RESEARCH INSTITUTE.KOL-63"},{"deceasedName":"AMAR NATH DHAR","yearOfregistration":"2014","dateOfRegistration":"","deathRegnNo":"10320","deathDate":"","crematoriumName":"M.G.E.C.(T)","deceasedSex":"MALE","crematoriumCode":"","fatherName":"LATE LAKSHMI NARAYAN DHAR","regnNo":"","deathSite":"THE MOTHER NURSING HOME"},{"deceasedName":"SHANTILATA BOSE","yearOfregistration":"2014","dateOfRegistration":"","deathRegnNo":"1895","deathDate":"","crematoriumName":"C.B.G.(T)","deceasedSex":"FEMALE","crematoriumCode":"","fatherName":"N.M","regnNo":"","deathSite":"R G KAR MEDICAL COLLEGE AND HOSPITAL KOL"},{"deceasedName":"GOUR CHANDRA DAS","yearOfregistration":"2014","dateOfRegistration":"","deathRegnNo":"10326","deathDate":"","crematoriumName":"M.G.E.C.(T)","deceasedSex":"MALE","crematoriumCode":"","fatherName":"LATE RATAN CHANDRA DAS","regnNo":"","deathSite":""},{"deceasedName":"GITA MONDAL","yearOfregistration":"2014","dateOfRegistration":"","deathRegnNo":"6703","deathDate":"","crematoriumName":"N.E.C.(T)","deceasedSex":"FEMALE","crematoriumCode":"","fatherName":"N/M","regnNo":"","deathSite":"N R S MEDICAL COLLEGE AND HOSPITAL. KOLKATA-14"},{"deceasedName":"PANCHA SINGH","yearOfregistration":"2014","dateOfRegistration":"","deathRegnNo":"9462","deathDate":"","crematoriumName":"C.M.H.O. SPL. REGISTRATION","deceasedSex":"MALE","crematoriumCode":"","fatherName":"KUSUM SINGH","regnNo":"","deathSite":"M.C.HOSPITAL. KOL"},{"deceasedName":"JADULAL SAHA","yearOfregistration":"2014","dateOfRegistration":"","deathRegnNo":"10249","deathDate":"","crematoriumName":"C.M.H.O. SPL. REGISTRATION","deceasedSex":"MALE","crematoriumCode":"","fatherName":"LATE RADHA BALLABH SAHA","regnNo":"","deathSite":"C.N.M.C AND HOSPITAL, KOLKATA-700014"},{"deceasedName":"SANTOSH CHOWDHURY","yearOfregistration":"2014","dateOfRegistration":"","deathRegnNo":"10330","deathDate":"","crematoriumName":"M.G.E.C.(T)","deceasedSex":"MALE","crematoriumCode":"","fatherName":"LATE BIJOY KRISHNA CHOWDHURY","regnNo":"","deathSite":""},{"deceasedName":"NAMITA MAJUMDAR","yearOfregistration":"2014","dateOfRegistration":"","deathRegnNo":"6686","deathDate":"","crematoriumName":"N.E.C.(T)","deceasedSex":"FEMALE","crematoriumCode":"","fatherName":"N/M","regnNo":"","deathSite":"N R S MEDICAL COLLEGE AND HOSPITAL. KOLKATA-14"},{"deceasedName":"MIRA SEN GUPTA","yearOfregistration":"2014","dateOfRegistration":"","deathRegnNo":"960","deathDate":"","crematoriumName":"K.M.B.G.(T)","deceasedSex":"FEMALE","crematoriumCode":"","fatherName":"X","regnNo":"","deathSite":"NORTH CITY HOSP.AND NEURO INST. PVT.LTD.,KOL"},{"deceasedName":"SHANTA BANERJEE","yearOfregistration":"2014","dateOfRegistration":"","deathRegnNo":"10324","deathDate":"","crematoriumName":"M.G.E.C.(T)","deceasedSex":"FEMALE","crematoriumCode":"","fatherName":"N/A","regnNo":"","deathSite":""},{"deceasedName":"TAPAS MONDAL","yearOfregistration":"2014","dateOfRegistration":"","deathRegnNo":"10619","deathDate":"","crematoriumName":"C.M.H.O. SPL. REGISTRATION","deceasedSex":"MALE","crematoriumCode":"","fatherName":"AMAR MONDAL","regnNo":"","deathSite":"M R BANGUR HOSPITAL,KOLKATA 700033"},{"deceasedName":"SK.AKHRAM","yearOfregistration":"2014","dateOfRegistration":"","deathRegnNo":"1358","deathDate":"","crematoriumName":"GOBRA B.G(T)","deceasedSex":"MALE","crematoriumCode":"","fatherName":"SK.GOLAM MD.","regnNo":"","deathSite":"CALCUTTA NATIONAL MEDICAL COLLEGE AND HOSP."},{"deceasedName":"PARAMESWAR MANDI","yearOfregistration":"2014","dateOfRegistration":"","deathRegnNo":"8910","deathDate":"","crematoriumName":"C.M.H.O. SPL. REGISTRATION","deceasedSex":"MALE","crematoriumCode":"","fatherName":"LATE JURU MANDI","regnNo":"","deathSite":"CENTRAL HOSPITAL. S.E. RAILWAY., GARDENREACH"},{"deceasedName":"SHYAMALENDU CHAUDHURY","yearOfregistration":"2014","dateOfRegistration":"","deathRegnNo":"10294","deathDate":"","crematoriumName":"M.G.E.C.(T)","deceasedSex":"MALE","crematoriumCode":"","fatherName":"LATE PRAMATHANATH CHAUDHURY","regnNo":"","deathSite":""},{"deceasedName":"JAGANNATH DHAR","yearOfregistration":"2014","dateOfRegistration":"","deathRegnNo":"6690","deathDate":"","crematoriumName":"N.E.C.(T)","deceasedSex":"MALE","crematoriumCode":"","fatherName":"LATE GOLOKENDRA NATH DHAR","regnNo":"","deathSite":"S.V.S. MARWARI HOSPITAL,KOLKATA 700009"},{"deceasedName":"MILON HALDAR","yearOfregistration":"2014","dateOfRegistration":"","deathRegnNo":"1696","deathDate":"","crematoriumName":"SIRITY B. GHAT E. (T)","deceasedSex":"MALE","crematoriumCode":"","fatherName":"KANU HALDAR","regnNo":"","deathSite":""},{"deceasedName":"SUBHAJIT SAHA","yearOfregistration":"2014","dateOfRegistration":"","deathRegnNo":"6691","deathDate":"","crematoriumName":"N.E.C.(T)","deceasedSex":"MALE","crematoriumCode":"","fatherName":"BIMAL KUMAR SAHA","regnNo":"","deathSite":"APOLLO GLENEAGLES HOSPITAL KOL-54"},{"deceasedName":"SAVITHRI SHARMA","yearOfregistration":"2014","dateOfRegistration":"","deathRegnNo":"783","deathDate":"","crematoriumName":"TOPSIA HINDU B.G.(T)","deceasedSex":"FEMALE","crematoriumCode":"","fatherName":"NOT MENTIONED","regnNo":"","deathSite":"CALCUTTA NATIONAL MEDICAL COLLEGE AND HOSP."},{"deceasedName":"ATIYAR RAHMAN","yearOfregistration":"2014","dateOfRegistration":"","deathRegnNo":"11357","deathDate":"","crematoriumName":"C.M.H.O. SPL. REGISTRATION","deceasedSex":"MALE","crematoriumCode":"","fatherName":"RAHIM BAKS","regnNo":"","deathSite":"KOLKATA SWASTHYA SANKALP,KOL-16"},{"deceasedName":"BISWANATH GHOSH","yearOfregistration":"2014","dateOfRegistration":"","deathRegnNo":"13323","deathDate":"","crematoriumName":"C.M.H.O. SPL. REGISTRATION","deceasedSex":"MALE","crematoriumCode":"","fatherName":"LATE BANKIM BIHARI GHOSH","regnNo":"","deathSite":"NETAJI SUBHASH NURSING HOME&DIAGNOSTIC CENTRE KOL-700023"},{"deceasedName":"ARCHANA KUNDU","yearOfregistration":"2014","dateOfRegistration":"","deathRegnNo":"13564","deathDate":"","crematoriumName":"C.M.H.O. SPL. REGISTRATION","deceasedSex":"FEMALE","crematoriumCode":"","fatherName":".................N/M...............","regnNo":"","deathSite":"KOTHARI  MEDICAL  CENTRE  KOL-27"},{"deceasedName":"LATIFA BIBI","yearOfregistration":"2015","dateOfRegistration":"","deathRegnNo":"7834","deathDate":"","crematoriumName":"C.M.H.O. SPL. REGISTRATION","deceasedSex":"FEMALE","crematoriumCode":"","fatherName":"-----------N/M----------------","regnNo":"","deathSite":"R G KAR MEDICAL COLLEGE AND HOSPITAL KOL"},{"deceasedName":"SUDHARANI KARMAKAR","yearOfregistration":"2014","dateOfRegistration":"","deathRegnNo":"10306","deathDate":"","crematoriumName":"M.G.E.C.(T)","deceasedSex":"FEMALE","crematoriumCode":"","fatherName":"N/A","regnNo":"","deathSite":""},{"deceasedName":"ADINATH MUKHERJEE","yearOfregistration":"2014","dateOfRegistration":"","deathRegnNo":"1698","deathDate":"","crematoriumName":"SIRITY B. GHAT E. (T)","deceasedSex":"MALE","crematoriumCode":"","fatherName":"LATE HARIBHUSAN MUKHERJEE","regnNo":"","deathSite":""},{"deceasedName":"NILRATAN MAITY","yearOfregistration":"2014","dateOfRegistration":"","deathRegnNo":"6696","deathDate":"","crematoriumName":"N.E.C.(T)","deceasedSex":"MALE","crematoriumCode":"","fatherName":"LATE JAHAR MAITY","regnNo":"","deathSite":""},{"deceasedName":"MENOKA TRIPATHI","yearOfregistration":"2014","dateOfRegistration":"","deathRegnNo":"6697","deathDate":"","crematoriumName":"N.E.C.(T)","deceasedSex":"FEMALE","crematoriumCode":"","fatherName":"N/M","regnNo":"","deathSite":""},{"deceasedName":"TARAPADA ROY","yearOfregistration":"2014","dateOfRegistration":"","deathRegnNo":"1876","deathDate":"","crematoriumName":"GARIA B.G.(T)","deceasedSex":"MALE","crematoriumCode":"","fatherName":"LATE FATIK CHANDRA ROY","regnNo":"","deathSite":""},{"deceasedName":"ARUN KUMAR BANERJEE","yearOfregistration":"2014","dateOfRegistration":"","deathRegnNo":"10329","deathDate":"","crematoriumName":"M.G.E.C.(T)","deceasedSex":"MALE","crematoriumCode":"","fatherName":"LATE S. K. BANERJEE","regnNo":"","deathSite":""},{"deceasedName":"RADHARANI BISWAS","yearOfregistration":"2014","dateOfRegistration":"","deathRegnNo":"963","deathDate":"","crematoriumName":"K.M.B.G.(T)","deceasedSex":"FEMALE","crematoriumCode":"","fatherName":"...","regnNo":"","deathSite":"WOODLANDS MULTISPECIALITY HOSP.LTD."},{"deceasedName":"PARITOSH ROY","yearOfregistration":"2014","dateOfRegistration":"","deathRegnNo":"9383","deathDate":"","crematoriumName":"C.M.H.O. SPL. REGISTRATION","deceasedSex":"MALE","crematoriumCode":"","fatherName":"LATE JOGENDRA MOHAN ROY","regnNo":"","deathSite":"APOLLO GLENEAGLES HOSPITAL KOL-54"},{"deceasedName":"SARASWATI SHAW","yearOfregistration":"2014","dateOfRegistration":"","deathRegnNo":"9552","deathDate":"","crematoriumName":"C.M.H.O. SPL. REGISTRATION","deceasedSex":"FEMALE","crematoriumCode":"","fatherName":"-----------N/M----------------","regnNo":"","deathSite":"PEERLESS HOSPITEX HOSPITAL AND RESEARCH CENTER LIMITED, KOLKATA-94."},{"deceasedName":"SAKTIBRATA MUKHERJEE","yearOfregistration":"2014","dateOfRegistration":"","deathRegnNo":"9678","deathDate":"","crematoriumName":"C.M.H.O. SPL. REGISTRATION","deceasedSex":"MALE","crematoriumCode":"","fatherName":"LATE SACHINDRA NATH MUKHERJEE","regnNo":"","deathSite":"MEDICA SUPERSPECIALTY HOSPITAL.KOL 99"},{"deceasedName":"SANKAR SARDAR","yearOfregistration":"2014","dateOfRegistration":"","deathRegnNo":"10365","deathDate":"","crematoriumName":"C.M.H.O. SPL. REGISTRATION","deceasedSex":"MALE","crematoriumCode":"","fatherName":"LATE KANGAL SARDAR","regnNo":"","deathSite":"C.N.M.C AND HOSPITAL, KOLKATA-700014"},{"deceasedName":"KAKALI ACHARYA","yearOfregistration":"2014","dateOfRegistration":"","deathRegnNo":"9599","deathDate":"","crematoriumName":"C.M.H.O. SPL. REGISTRATION","deceasedSex":"FEMALE","crematoriumCode":"","fatherName":"N.M","regnNo":"","deathSite":"B.R.SINGH HOSPITAL,KOLKATA"},{"deceasedName":"NIRANJAN HALDER","yearOfregistration":"2014","dateOfRegistration":"","deathRegnNo":"6700","deathDate":"","crematoriumName":"N.E.C.(T)","deceasedSex":"MALE","crematoriumCode":"","fatherName":"LATE PHANI BHUSAN HALDER","regnNo":"","deathSite":"R G KAR MEDICAL COLLEGE AND HOSPITAL KOL"},{"deceasedName":"PROBIR ROY","yearOfregistration":"2014","dateOfRegistration":"","deathRegnNo":"10325","deathDate":"","crematoriumName":"M.G.E.C.(T)","deceasedSex":"MALE","crematoriumCode":"","fatherName":"LATE BANBEHARI ROY","regnNo":"","deathSite":""},{"deceasedName":"BABLU MONDAL","yearOfregistration":"2014","dateOfRegistration":"","deathRegnNo":"10353","deathDate":"","crematoriumName":"M.G.E.C.(T)","deceasedSex":"MALE","crematoriumCode":"","fatherName":"BADAL MONDAL","regnNo":"","deathSite":"VIDYASAGAR S.G. HOSPITAL BEHALA KOL"},{"deceasedName":"AJIT KUMAR BHATTACHARJEE","yearOfregistration":"2014","dateOfRegistration":"","deathRegnNo":"1870","deathDate":"","crematoriumName":"GARIA B.G.(T)","deceasedSex":"MALE","crematoriumCode":"","fatherName":"LATE ANANGA MOHAN BHATTACHARJEE","regnNo":"","deathSite":""},{"deceasedName":"DIPALI CHANDA","yearOfregistration":"2014","dateOfRegistration":"","deathRegnNo":"10315","deathDate":"","crematoriumName":"M.G.E.C.(T)","deceasedSex":"FEMALE","crematoriumCode":"","fatherName":"N/A","regnNo":"","deathSite":"KPC MEDICAL COLLEGE AND HOSPITAL,JADAVPUR"},{"deceasedName":"CHATUR BHUVAN PRASAD SINGH","yearOfregistration":"2014","dateOfRegistration":"","deathRegnNo":"1082","deathDate":"","crematoriumName":"N.B.G.(T)","deceasedSex":"MALE","crematoriumCode":"","fatherName":"LATE BAIDYA NATH SINGH","regnNo":"","deathSite":""},{"deceasedName":"TARUBALA KUNDU","yearOfregistration":"2014","dateOfRegistration":"","deathRegnNo":"6683","deathDate":"","crematoriumName":"N.E.C.(T)","deceasedSex":"FEMALE","crematoriumCode":"","fatherName":"N/M","regnNo":"","deathSite":""},{"deceasedName":"B/O NAMITA GHOSH","yearOfregistration":"2014","dateOfRegistration":"","deathRegnNo":"782","deathDate":"","crematoriumName":"TOPSIA HINDU B.G.(T)","deceasedSex":"FEMALE","crematoriumCode":"","fatherName":"PINTU GHOSH","regnNo":"","deathSite":"CALCUTTA NATIONAL MEDICAL COLLEGE AND HOSP."},{"deceasedName":"HANSHI DUTTA","yearOfregistration":"2014","dateOfRegistration":"","deathRegnNo":"6684","deathDate":"","crematoriumName":"N.E.C.(T)","deceasedSex":"FEMALE","crematoriumCode":"","fatherName":"N/M","regnNo":"","deathSite":""},{"deceasedName":"TARU BALA KARMAKAR","yearOfregistration":"2014","dateOfRegistration":"","deathRegnNo":"1873","deathDate":"","crematoriumName":"GARIA B.G.(T)","deceasedSex":"FEMALE","crematoriumCode":"","fatherName":"N/M","regnNo":"","deathSite":""},{"deceasedName":"SHIBANI BANERJEE","yearOfregistration":"2014","dateOfRegistration":"","deathRegnNo":"959","deathDate":"","crematoriumName":"K.M.B.G.(T)","deceasedSex":"FEMALE","crematoriumCode":"","fatherName":"X","regnNo":"","deathSite":"N R S MEDICAL COLLEGE AND HOSPITAL. KOLKATA-14"},{"deceasedName":"KALYAN KUMAR PAUL","yearOfregistration":"2014","dateOfRegistration":"","deathRegnNo":"10318","deathDate":"","crematoriumName":"M.G.E.C.(T)","deceasedSex":"MALE","crematoriumCode":"","fatherName":"LATE PARESH KRISHNA PAUL","regnNo":"","deathSite":""},{"deceasedName":"FULU DAS","yearOfregistration":"2014","dateOfRegistration":"","deathRegnNo":"6698","deathDate":"","crematoriumName":"N.E.C.(T)","deceasedSex":"MALE","crematoriumCode":"","fatherName":"LATE RAJU DAS","regnNo":"","deathSite":""},{"deceasedName":"RAM BABU SINGH","yearOfregistration":"2014","dateOfRegistration":"","deathRegnNo":"10319","deathDate":"","crematoriumName":"M.G.E.C.(T)","deceasedSex":"MALE","crematoriumCode":"","fatherName":"LATE NATHUN SINGH","regnNo":"","deathSite":"SAMBHU NATH PANDIT HOSPITAL,KOL"},{"deceasedName":"HASINA KHATOON","yearOfregistration":"2014","dateOfRegistration":"","deathRegnNo":"406","deathDate":"","crematoriumName":"BAGMARI B.G. (T)","deceasedSex":"FEMALE","crematoriumCode":"","fatherName":"--------------N/M------------","regnNo":"","deathSite":""},{"deceasedName":"SAILENDRA NATH BHATTACHARJEE","yearOfregistration":"2014","dateOfRegistration":"","deathRegnNo":"10323","deathDate":"","crematoriumName":"M.G.E.C.(T)","deceasedSex":"MALE","crematoriumCode":"","fatherName":"LATE SATYA BHUSAN BHATTACHARJEE","regnNo":"","deathSite":"S S K M HOSPITAL. KOLKATA"},{"deceasedName":"HARAPRASAD GHOSE","yearOfregistration":"2014","dateOfRegistration":"","deathRegnNo":"961","deathDate":"","crematoriumName":"K.M.B.G.(T)","deceasedSex":"MALE","crematoriumCode":"","fatherName":"LATE BIBHUTI BHUSAN GHOSE","regnNo":"","deathSite":""},{"deceasedName":"SAILAJANATH BANERJEE","yearOfregistration":"2014","dateOfRegistration":"","deathRegnNo":"1875","deathDate":"","crematoriumName":"GARIA B.G.(T)","deceasedSex":"MALE","crematoriumCode":"","fatherName":"LATE BHUSAN BANERJEE","regnNo":"","deathSite":"KPC MEDICAL COLLEGE AND HOSPITAL,JADAVPUR"},{"deceasedName":"RANJIT PRASAD","yearOfregistration":"2014","dateOfRegistration":"","deathRegnNo":"6704","deathDate":"","crematoriumName":"N.E.C.(T)","deceasedSex":"MALE","crematoriumCode":"","fatherName":"LATE BHIKARI PRASAD","regnNo":"","deathSite":"MEDICAL COLLEGE AND HOSPITAL,KOLKATA 73"},{"deceasedName":"SHANTA MALIK","yearOfregistration":"2014","dateOfRegistration":"","deathRegnNo":"6705","deathDate":"","crematoriumName":"N.E.C.(T)","deceasedSex":"MALE","crematoriumCode":"","fatherName":"LATE SHIBU MALIK","regnNo":"","deathSite":"R G KAR MEDICAL COLLEGE AND HOSPITAL KOL"},{"deceasedName":"BROJESWARI NASKAR","yearOfregistration":"2014","dateOfRegistration":"","deathRegnNo":"128","deathDate":"","crematoriumName":"BR EX. H. O.  XIV SPL.","deceasedSex":"FEMALE","crematoriumCode":"","fatherName":"LATE KEDAR MONDAL","regnNo":"","deathSite":"ESIC HOSP. AND OCCUPATIONAL DISEASE CENTRE(EZ)"},{"deceasedName":"ANJALI DAS","yearOfregistration":"2014","dateOfRegistration":"","deathRegnNo":"6680","deathDate":"","crematoriumName":"N.E.C.(T)","deceasedSex":"FEMALE","crematoriumCode":"","fatherName":"N/M","regnNo":"","deathSite":"CALCUTTA PAVLOV HOSPITAL KOL-46"},{"deceasedName":"ANIMA ROY","yearOfregistration":"2014","dateOfRegistration":"","deathRegnNo":"10969","deathDate":"","crematoriumName":"C.M.H.O. SPL. REGISTRATION","deceasedSex":"FEMALE","crematoriumCode":"","fatherName":"N.M","regnNo":"","deathSite":"E.S.I. HOSPITAL,MANICKTALA,KOLKATA-54"},{"deceasedName":"MOUMITA CHAKRABORTY","yearOfregistration":"2014","dateOfRegistration":"","deathRegnNo":"9968","deathDate":"","crematoriumName":"C.M.H.O. SPL. REGISTRATION","deceasedSex":"FEMALE","crematoriumCode":"","fatherName":"N.M","regnNo":"","deathSite":"M.C.HOSPITAL. KOL"},{"deceasedName":"GITA RANI LOW","yearOfregistration":"2014","dateOfRegistration":"","deathRegnNo":"10097","deathDate":"","crematoriumName":"C.M.H.O. SPL. REGISTRATION","deceasedSex":"FEMALE","crematoriumCode":"","fatherName":"-----------N/M----------------","regnNo":"","deathSite":"INSTITUTE OF NEUROSCIENCES, KOL"},{"deceasedName":"RAMAPADA MONDAL","yearOfregistration":"2014","dateOfRegistration":"","deathRegnNo":"10072","deathDate":"","crematoriumName":"C.M.H.O. SPL. REGISTRATION","deceasedSex":"MALE","crematoriumCode":"","fatherName":"LATE JATIN MONDAL","regnNo":"","deathSite":"M.C.HOSPITAL. KOL"},{"deceasedName":"SATYA RANJAN DAS","yearOfregistration":"2014","dateOfRegistration":"","deathRegnNo":"6682","deathDate":"","crematoriumName":"N.E.C.(T)","deceasedSex":"MALE","crematoriumCode":"","fatherName":"S/O LATE RASHMOHAN DAS","regnNo":"","deathSite":""},{"deceasedName":"BHAGABATI BAYEN","yearOfregistration":"2014","dateOfRegistration":"","deathRegnNo":"6695","deathDate":"","crematoriumName":"N.E.C.(T)","deceasedSex":"FEMALE","crematoriumCode":"","fatherName":"N/M","regnNo":"","deathSite":""},{"deceasedName":"RAJU MONDAL","yearOfregistration":"2014","dateOfRegistration":"","deathRegnNo":"10124","deathDate":"","crematoriumName":"C.M.H.O. SPL. REGISTRATION","deceasedSex":"MALE","crematoriumCode":"","fatherName":"RASHID MONDAL","regnNo":"","deathSite":"S S K M HOSPITAL. KOLKATA"},{"deceasedName":"PRABIR BOSE","yearOfregistration":"2014","dateOfRegistration":"","deathRegnNo":"957","deathDate":"","crematoriumName":"K.M.B.G.(T)","deceasedSex":"MALE","crematoriumCode":"","fatherName":"LATE JYOTSNA BOSE","regnNo":"","deathSite":""},{"deceasedName":"URMILA DAS","yearOfregistration":"2014","dateOfRegistration":"","deathRegnNo":"958","deathDate":"","crematoriumName":"K.M.B.G.(T)","deceasedSex":"FEMALE","crematoriumCode":"","fatherName":"N.A.","regnNo":"","deathSite":"R G KAR MEDICAL COLLEGE AND HOSPITAL KOL"},{"deceasedName":"DEBI PRASAD BOSE","yearOfregistration":"2014","dateOfRegistration":"","deathRegnNo":"10301","deathDate":"","crematoriumName":"M.G.E.C.(T)","deceasedSex":"MALE","crematoriumCode":"","fatherName":"LATE DWIJENDRA NATH BOSE","regnNo":"","deathSite":""},{"deceasedName":"RASHIK LAL PODDAR","yearOfregistration":"2014","dateOfRegistration":"","deathRegnNo":"10948","deathDate":"","crematoriumName":"C.M.H.O. SPL. REGISTRATION","deceasedSex":"MALE","crematoriumCode":"","fatherName":"LATE SATISH CHANDRA PODDAR","regnNo":"","deathSite":"M.C.HOSPITAL. KOL"},{"deceasedName":"SUSHIL MONDAL","yearOfregistration":"2014","dateOfRegistration":"","deathRegnNo":"1694","deathDate":"","crematoriumName":"SIRITY B. GHAT E. (T)","deceasedSex":"MALE","crematoriumCode":"","fatherName":"LATE ANIL MONDAL","regnNo":"","deathSite":"PEERLESS HOSPITAL AND B.K.ROY RESEARCH CENTRE,KOLKATA"},{"deceasedName":"NETAI JANA","yearOfregistration":"2014","dateOfRegistration":"","deathRegnNo":"6749","deathDate":"","crematoriumName":"N.E.C.(T)","deceasedSex":"MALE","crematoriumCode":"","fatherName":"LT BIPIN JANA","regnNo":"","deathSite":""},{"deceasedName":"TOSADDAQUE PIR","yearOfregistration":"2014","dateOfRegistration":"","deathRegnNo":"9116","deathDate":"","crematoriumName":"C.M.H.O. SPL. REGISTRATION","deceasedSex":"MALE","crematoriumCode":"","fatherName":"LATE GOLAM PIR","regnNo":"","deathSite":"S S K M HOSPITAL. KOLKATA"},{"deceasedName":"FATICK CHANDRA KARMAKAR","yearOfregistration":"2014","dateOfRegistration":"","deathRegnNo":"9377","deathDate":"","crematoriumName":"C.M.H.O. SPL. REGISTRATION","deceasedSex":"MALE","crematoriumCode":"","fatherName":"LATE KALIPADA KARMAKAR","regnNo":"","deathSite":"PEERLESS HOSPITEX HOSPITAL AND RESEARCH CENTER LIMITED, KOLKATA-94."},{"deceasedName":"AKHTAR  ALAM","yearOfregistration":"2014","dateOfRegistration":"","deathRegnNo":"902","deathDate":"","crematoriumName":"SOLOAANA B.G.(T)","deceasedSex":"MALE","crematoriumCode":"","fatherName":"LATE  ISMAIL  MOHAMMED","regnNo":"","deathSite":"LABBAIK MEDICAL CENTRE PVT. LTD."},{"deceasedName":"SABITA SAHA","yearOfregistration":"2014","dateOfRegistration":"","deathRegnNo":"1871","deathDate":"","crematoriumName":"GARIA B.G.(T)","deceasedSex":"FEMALE","crematoriumCode":"","fatherName":"LATE HARI PADA SAHA","regnNo":"","deathSite":"S S K M HOSPITAL. KOLKATA"},{"deceasedName":"DEBDAS HALDER","yearOfregistration":"2014","dateOfRegistration":"","deathRegnNo":"10312","deathDate":"","crematoriumName":"M.G.E.C.(T)","deceasedSex":"MALE","crematoriumCode":"","fatherName":"LATE SADHAN HALDER","regnNo":"","deathSite":"RABINDRANATH TAGORE INTERNATIONAL INSTITUTE OF CARDIAC SCIENCES,KOLKATA-99"},{"deceasedName":"SUKUMAR SAHA","yearOfregistration":"2014","dateOfRegistration":"","deathRegnNo":"1866","deathDate":"","crematoriumName":"GARIA B.G.(T)","deceasedSex":"MALE","crematoriumCode":"","fatherName":"LATE ABINASH CHANDRA SAHA","regnNo":"","deathSite":"RABINDRANATH TAGORE INTERNATIONAL INSTITUTE OF CARDIAC SCIENCES,KOLKATA-99"},{"deceasedName":"B/O-JAHIDA BIBI(S.B)","yearOfregistration":"2014","dateOfRegistration":"","deathRegnNo":"1355","deathDate":"","crematoriumName":"GOBRA B.G(T)","deceasedSex":"MALE","crematoriumCode":"","fatherName":"SK.KALIMUDDIN ALIAS SK.KOLIMUDDIN","regnNo":"","deathSite":"C.N.M.C AND HOSPITAL, KOLKATA-700014"},{"deceasedName":"ZAHOOR AHMED","yearOfregistration":"2014","dateOfRegistration":"","deathRegnNo":"1359","deathDate":"","crematoriumName":"GOBRA B.G(T)","deceasedSex":"MALE","crematoriumCode":"","fatherName":"LATE ABDUR RAHMAN","regnNo":"","deathSite":""},{"deceasedName":"SARAMA DUTTA","yearOfregistration":"2014","dateOfRegistration":"","deathRegnNo":"6708","deathDate":"","crematoriumName":"N.E.C.(T)","deceasedSex":"FEMALE","crematoriumCode":"","fatherName":"N/M","regnNo":"","deathSite":"MEDICAL COLLEGE AND HOSPITAL,KOLKATA 73"},{"deceasedName":"RINA CHOWDHURY","yearOfregistration":"2014","dateOfRegistration":"","deathRegnNo":"10339","deathDate":"","crematoriumName":"M.G.E.C.(T)","deceasedSex":"FEMALE","crematoriumCode":"","fatherName":"LATE ROHINI LAL CHOWDHURY","regnNo":"","deathSite":""},{"deceasedName":"NANDADULAL DE","yearOfregistration":"2014","dateOfRegistration":"","deathRegnNo":"10299","deathDate":"","crematoriumName":"M.G.E.C.(T)","deceasedSex":"MALE","crematoriumCode":"","fatherName":"N/A","regnNo":"","deathSite":"SAROJ GUPTA CANCER CENTRE & RESEARCH INSTITUTE.KOL-63"},{"deceasedName":"PURNIMA ROY","yearOfregistration":"2014","dateOfRegistration":"","deathRegnNo":"10302","deathDate":"","crematoriumName":"M.G.E.C.(T)","deceasedSex":"FEMALE","crematoriumCode":"","fatherName":"N/A","regnNo":"","deathSite":""},{"deceasedName":"BIJOY BHUSAN DAS","yearOfregistration":"2014","dateOfRegistration":"","deathRegnNo":"1867","deathDate":"","crematoriumName":"GARIA B.G.(T)","deceasedSex":"MALE","crematoriumCode":"","fatherName":"LATE GANESH CH.DAS","regnNo":"","deathSite":"M R BANGUR HOSPITAL,KOLKATA 700033"},{"deceasedName":"GOURDASI KARMAKAR","yearOfregistration":"2014","dateOfRegistration":"","deathRegnNo":"6706","deathDate":"","crematoriumName":"N.E.C.(T)","deceasedSex":"FEMALE","crematoriumCode":"","fatherName":"N/M","regnNo":"","deathSite":"SHUSRUSHA NURSING HOME (P) LTD"},{"deceasedName":"RUPALI SARKAR","yearOfregistration":"2014","dateOfRegistration":"","deathRegnNo":"6707","deathDate":"","crematoriumName":"N.E.C.(T)","deceasedSex":"FEMALE","crematoriumCode":"","fatherName":"N/M","regnNo":"","deathSite":"S S K M HOSPITAL. KOLKATA"},{"deceasedName":"DILIP KUMAR SAHA","yearOfregistration":"2014","dateOfRegistration":"","deathRegnNo":"10334","deathDate":"","crematoriumName":"M.G.E.C.(T)","deceasedSex":"MALE","crematoriumCode":"","fatherName":"LATE RAMANI MOHAN SAHA","regnNo":"","deathSite":"CURE CENTRE NURSING HOME"},{"deceasedName":"MAHENDRA NATH MANNA","yearOfregistration":"2014","dateOfRegistration":"","deathRegnNo":"1702","deathDate":"","crematoriumName":"SIRITY B. GHAT E. (T)","deceasedSex":"MALE","crematoriumCode":"","fatherName":"LATE KRISHNA PRASAD MANNA","regnNo":"","deathSite":""},{"deceasedName":"FIROZ JAMADAR","yearOfregistration":"2014","dateOfRegistration":"","deathRegnNo":"9645","deathDate":"","crematoriumName":"C.M.H.O. SPL. REGISTRATION","deceasedSex":"MALE","crematoriumCode":"","fatherName":"IDRISH JAMADAR","regnNo":"","deathSite":"M.C.HOSPITAL. KOL"},{"deceasedName":"RANJIT ROY","yearOfregistration":"2014","dateOfRegistration":"","deathRegnNo":"6719","deathDate":"","crematoriumName":"N.E.C.(T)","deceasedSex":"MALE","crematoriumCode":"","fatherName":"S/O LT. ANIL CH. ROY","regnNo":"","deathSite":""},{"deceasedName":"UNKNOWN SINCE KNOWN AS  LAYLY BIBI","yearOfregistration":"2014","dateOfRegistration":"","deathRegnNo":"1371","deathDate":"","crematoriumName":"GOBRA B.G(T)","deceasedSex":"FEMALE","crematoriumCode":"","fatherName":".........N/M........","regnNo":"","deathSite":"N R S MEDICAL COLLEGE AND HOSPITAL. KOLKATA-14"},{"deceasedName":"PRATIMA MONDAL","yearOfregistration":"2014","dateOfRegistration":"","deathRegnNo":"1868","deathDate":"","crematoriumName":"GARIA B.G.(T)","deceasedSex":"FEMALE","crematoriumCode":"","fatherName":"SANJAY MONDAL","regnNo":"","deathSite":"IRIS HOSPITAL KOL-47"},{"deceasedName":"KETAKI GANGULY","yearOfregistration":"2014","dateOfRegistration":"","deathRegnNo":"965","deathDate":"","crematoriumName":"K.M.B.G.(T)","deceasedSex":"FEMALE","crematoriumCode":"","fatherName":"W/O LATE JAGADISH CHANDRA GANGULY","regnNo":"","deathSite":"GD HOSPITAL AND DIABETES INSTITUTE,KOLKATA'13"},{"deceasedName":"MANOJ KUMAR KEDIA","yearOfregistration":"2014","dateOfRegistration":"","deathRegnNo":"9724","deathDate":"","crematoriumName":"C.M.H.O. SPL. REGISTRATION","deceasedSex":"MALE","crematoriumCode":"","fatherName":".................N/M...............","regnNo":"","deathSite":"R K M SEVA PRATISHTHAN.  KOL-26"},{"deceasedName":"RUPA DAS","yearOfregistration":"2014","dateOfRegistration":"","deathRegnNo":"9887","deathDate":"","crematoriumName":"C.M.H.O. SPL. REGISTRATION","deceasedSex":"FEMALE","crematoriumCode":"","fatherName":"-----------N/M----------------","regnNo":"","deathSite":"N R S MEDICAL COLLEGE AND HOSPITAL. KOLKATA-14"},{"deceasedName":"SRIDHAR GHOSH","yearOfregistration":"2014","dateOfRegistration":"","deathRegnNo":"9810","deathDate":"","crematoriumName":"C.M.H.O. SPL. REGISTRATION","deceasedSex":"MALE","crematoriumCode":"","fatherName":"LATE SURENDRA NATH GHOSH","regnNo":"","deathSite":"NORTH CITY HOSP.AND NEURO INST. PVT.LTD.,KOL"},{"deceasedName":"PIJUSH KANTI GHOSH","yearOfregistration":"2014","dateOfRegistration":"","deathRegnNo":"10308","deathDate":"","crematoriumName":"M.G.E.C.(T)","deceasedSex":"MALE","crematoriumCode":"","fatherName":"LATE DR. BHABESH CHANDRA GHOSH","regnNo":"","deathSite":"RUBY GENERAL HOSPITAL KOLKATA"},{"deceasedName":"MAYOOKH KANTI MUNSI","yearOfregistration":"2014","dateOfRegistration":"","deathRegnNo":"1894","deathDate":"","crematoriumName":"C.B.G.(T)","deceasedSex":"MALE","crematoriumCode":"","fatherName":"S/O-LATE ASIT KANTI MUNSI","regnNo":"","deathSite":"FORTIS HOSPITALS, KOLKATA '700107"},{"deceasedName":"SANDHYA MUKHERJEE","yearOfregistration":"2014","dateOfRegistration":"","deathRegnNo":"6689","deathDate":"","crematoriumName":"N.E.C.(T)","deceasedSex":"FEMALE","crematoriumCode":"","fatherName":"N/M","regnNo":"","deathSite":"S S K M HOSPITAL. KOLKATA"},{"deceasedName":"NANIBALA DAS","yearOfregistration":"2014","dateOfRegistration":"","deathRegnNo":"10317","deathDate":"","crematoriumName":"M.G.E.C.(T)","deceasedSex":"FEMALE","crematoriumCode":"","fatherName":"N/A","regnNo":"","deathSite":"VIVEKANANDA HOSPITAL AND R.I.KOLKATA"},{"deceasedName":"SAKTI KUMAR BASU","yearOfregistration":"2014","dateOfRegistration":"","deathRegnNo":"1874","deathDate":"","crematoriumName":"GARIA B.G.(T)","deceasedSex":"MALE","crematoriumCode":"","fatherName":"LATE NARAYAN KUMAR BASU","regnNo":"","deathSite":"PEERLESS HOSPITEX HOSPITAL AND RESEARCH CENTER LIMITED, KOLKATA-94."},{"deceasedName":"BADAL RANI SARKAR","yearOfregistration":"2014","dateOfRegistration":"","deathRegnNo":"1699","deathDate":"","crematoriumName":"SIRITY B. GHAT E. (T)","deceasedSex":"FEMALE","crematoriumCode":"","fatherName":"N/M","regnNo":"","deathSite":""},{"deceasedName":"SK ABBAS","yearOfregistration":"2014","dateOfRegistration":"","deathRegnNo":"54","deathDate":"","crematoriumName":"MOLLA HAT KABARSTHAN(PGMSBG)","deceasedSex":"MALE","crematoriumCode":"","fatherName":"LATE SK SAMSUDDIN","regnNo":"","deathSite":"MEDLINE NURSING HOME"},{"deceasedName":"SUBAL DAS","yearOfregistration":"2015","dateOfRegistration":"","deathRegnNo":"5225","deathDate":"","crematoriumName":"C.M.H.O. SPL. REGISTRATION","deceasedSex":"MALE","crematoriumCode":"","fatherName":"LT. GOPAL DAS","regnNo":"","deathSite":"N R S MEDICAL COLLEGE AND HOSPITAL. KOLKATA-14"},{"deceasedName":"SABITA SIKDER","yearOfregistration":"2015","dateOfRegistration":"","deathRegnNo":"7140","deathDate":"","crematoriumName":"C.M.H.O. SPL. REGISTRATION","deceasedSex":"FEMALE","crematoriumCode":"","fatherName":"N.M","regnNo":"","deathSite":"S S K M HOSPITAL. KOLKATA"},{"deceasedName":"BINDU BASINI SIL","yearOfregistration":"2015","dateOfRegistration":"","deathRegnNo":"2659","deathDate":"","crematoriumName":"C.M.H.O. SPL. REGISTRATION","deceasedSex":"FEMALE","crematoriumCode":"","fatherName":"N.M","regnNo":"","deathSite":"S S K M HOSPITAL. KOLKATA"},{"deceasedName":"SUNETRA KANTI BARMAN ROY","yearOfregistration":"2014","dateOfRegistration":"","deathRegnNo":"12602","deathDate":"","crematoriumName":"C.M.H.O. SPL. REGISTRATION","deceasedSex":"MALE","crematoriumCode":"","fatherName":"LATE JITENDRA CHANDRA BARMAN ROY","regnNo":"","deathSite":"COMMAND HOSPITAL (E.C.) KOL"},{"deceasedName":"KANTI DEVI","yearOfregistration":"2014","dateOfRegistration":"","deathRegnNo":"12540","deathDate":"","crematoriumName":"C.M.H.O. SPL. REGISTRATION","deceasedSex":"FEMALE","crematoriumCode":"","fatherName":"N.M","regnNo":"","deathSite":"M.C.HOSPITAL. KOL"},{"deceasedName":"SUMITRA DEVI","yearOfregistration":"2014","dateOfRegistration":"","deathRegnNo":"11913","deathDate":"","crematoriumName":"C.M.H.O. SPL. REGISTRATION","deceasedSex":"FEMALE","crematoriumCode":"","fatherName":"-----------N/M----------------","regnNo":"","deathSite":"NETAJI SUBHAS CHANDRA BOSE CANCER RESEARCH INSTITUTE KOL"},{"deceasedName":"RAM BILAS SAHANI","yearOfregistration":"2014","dateOfRegistration":"","deathRegnNo":"12287","deathDate":"","crematoriumName":"C.M.H.O. SPL. REGISTRATION","deceasedSex":"MALE","crematoriumCode":"","fatherName":"LATE TETAR SAHANI","regnNo":"","deathSite":"APOLLO GLENEAGLES HOSPITAL KOL-54"},{"deceasedName":"TUSHER KANTI GHOSH","yearOfregistration":"2014","dateOfRegistration":"","deathRegnNo":"12288","deathDate":"","crematoriumName":"C.M.H.O. SPL. REGISTRATION","deceasedSex":"MALE","crematoriumCode":"","fatherName":"LATE DURGAPADA GHOSH","regnNo":"","deathSite":"PEERLESS HOSPITAL AND B.K.ROY RESEARCH CENTRE,KOLKATA"},{"deceasedName":"KABITA BAG","yearOfregistration":"2015","dateOfRegistration":"","deathRegnNo":"1674","deathDate":"","crematoriumName":"C.M.H.O. SPL. REGISTRATION","deceasedSex":"FEMALE","crematoriumCode":"","fatherName":"N.M","regnNo":"","deathSite":"NETAJI SUBHAS CHANDRA BOSE CANCER RESEARCH INSTITUTE KOL"}]}