{success:true,deathRecords:[{"deceasedName":"TRIPTI GHOSH","yearOfregistration":"2016","dateOfRegistration":"","deathRegnNo":"4430","deathDate":"","crematoriumName":"C.M.H.O. SPL. REGISTRATION","deceasedSex":"FEMALE","crematoriumCode":"","fatherName":"N.M","regnNo":"","deathSite":"KPC MEDICAL COLLEGE AND HOSPITAL,JADAVPUR"},{"deceasedName":"GHANASHYAM TALANGE","yearOfregistration":"2016","dateOfRegistration":"","deathRegnNo":"2500","deathDate":"","crematoriumName":"N.E.C.(T)","deceasedSex":"MALE","crematoriumCode":"","fatherName":"S/O.LATE. SHAYAM BAHADUR TALANGE","regnNo":"","deathSite":"N R S MEDICAL COLLEGE AND HOSPITAL. KOLKATA-14"},{"deceasedName":"KUNTI DEVI SHAW","yearOfregistration":"2016","dateOfRegistration":"","deathRegnNo":"2503","deathDate":"","crematoriumName":"N.E.C.(T)","deceasedSex":"FEMALE","crematoriumCode":"","fatherName":"N/M","regnNo":"","deathSite":""},{"deceasedName":"A BABY","yearOfregistration":"2016","dateOfRegistration":"","deathRegnNo":"92","deathDate":"","crematoriumName":"MURARIPUKUR B.G. (T)","deceasedSex":"MALE","crematoriumCode":"","fatherName":"TARUN GHOSH","regnNo":"","deathSite":"B.C. ROY  CHILD  HOSP."},{"deceasedName":"BASANTA KUMAR DAS","yearOfregistration":"2016","dateOfRegistration":"","deathRegnNo":"2505","deathDate":"","crematoriumName":"N.E.C.(T)","deceasedSex":"MALE","crematoriumCode":"","fatherName":"S/O.LATE. SAMBHU NATH DAS","regnNo":"","deathSite":""},{"deceasedName":"GOUTAM PAUL","yearOfregistration":"2016","dateOfRegistration":"","deathRegnNo":"2509","deathDate":"","crematoriumName":"N.E.C.(T)","deceasedSex":"MALE","crematoriumCode":"","fatherName":"LATE. DHIRENDRA NATH PAUL","regnNo":"","deathSite":"R G KAR MEDICAL COLLEGE AND HOSPITAL KOL"},{"deceasedName":"LATIKA SADHU @ SADHUKHAN","yearOfregistration":"2016","dateOfRegistration":"","deathRegnNo":"2511","deathDate":"","crematoriumName":"N.E.C.(T)","deceasedSex":"FEMALE","crematoriumCode":"","fatherName":"D/O.LATE. PRAFULLA KUMAR SADHUKHAN","regnNo":"","deathSite":""},{"deceasedName":"GOPAL HALDER","yearOfregistration":"2016","dateOfRegistration":"","deathRegnNo":"525","deathDate":"","crematoriumName":"C.B.G.(T)","deceasedSex":"MALE","crematoriumCode":"","fatherName":"LATE ADHAR HALDER","regnNo":"","deathSite":""},{"deceasedName":"SANTA CHATTERJEE","yearOfregistration":"2016","dateOfRegistration":"","deathRegnNo":"3460","deathDate":"","crematoriumName":"M.G.E.C.(T)","deceasedSex":"FEMALE","crematoriumCode":"","fatherName":"N/A","regnNo":"","deathSite":"DR. B.N. BASU MEMORIAL CLINIC APOLLO N.H."},{"deceasedName":"SHANTA ACHARYA","yearOfregistration":"2016","dateOfRegistration":"","deathRegnNo":"3461","deathDate":"","crematoriumName":"M.G.E.C.(T)","deceasedSex":"FEMALE","crematoriumCode":"","fatherName":"N/A","regnNo":"","deathSite":""},{"deceasedName":"TAPATI MOITRA","yearOfregistration":"2016","dateOfRegistration":"","deathRegnNo":"3436","deathDate":"","crematoriumName":"M.G.E.C.(T)","deceasedSex":"FEMALE","crematoriumCode":"","fatherName":"N/A","regnNo":"","deathSite":""},{"deceasedName":"RAMEN BAIRAGI","yearOfregistration":"2016","dateOfRegistration":"","deathRegnNo":"2494","deathDate":"","crematoriumName":"N.E.C.(T)","deceasedSex":"MALE","crematoriumCode":"","fatherName":"LATE JALADHAR BAIRAGI","regnNo":"","deathSite":"R G KAR MEDICAL COLLEGE AND HOSPITAL KOL"},{"deceasedName":"MAHABIR PRASAD SARAOGI","yearOfregistration":"2016","dateOfRegistration":"","deathRegnNo":"2517","deathDate":"","crematoriumName":"N.E.C.(T)","deceasedSex":"MALE","crematoriumCode":"","fatherName":"S/O.LATE. RAM KUMAR SARAOGI","regnNo":"","deathSite":""},{"deceasedName":"FULU PUNGA","yearOfregistration":"2016","dateOfRegistration":"","deathRegnNo":"3426","deathDate":"","crematoriumName":"M.G.E.C.(T)","deceasedSex":"FEMALE","crematoriumCode":"","fatherName":"N/A","regnNo":"","deathSite":"CENTRAL HOSPITAL. S.E. RAILWAY., GARDENREACH"},{"deceasedName":"RATAN SIL","yearOfregistration":"2016","dateOfRegistration":"","deathRegnNo":"3474","deathDate":"","crematoriumName":"M.G.E.C.(T)","deceasedSex":"MALE","crematoriumCode":"","fatherName":"LATE KHETRA MOHON SIL","regnNo":"","deathSite":"E.S.I. HOSP., SEALDAH"},{"deceasedName":"UMA DEY","yearOfregistration":"2016","dateOfRegistration":"","deathRegnNo":"667","deathDate":"","crematoriumName":"GARIA B.G.(T)","deceasedSex":"FEMALE","crematoriumCode":"","fatherName":"NOT MENTION","regnNo":"","deathSite":"C.N.M.C AND HOSPITAL, KOLKATA-700014"},{"deceasedName":"RAJAT KUMAR PANDEY","yearOfregistration":"2016","dateOfRegistration":"","deathRegnNo":"3464","deathDate":"","crematoriumName":"M.G.E.C.(T)","deceasedSex":"MALE","crematoriumCode":"","fatherName":"S/O LATE TARA KUMAR PANDEY","regnNo":"","deathSite":""},{"deceasedName":"AMAR GHOSH","yearOfregistration":"2016","dateOfRegistration":"","deathRegnNo":"3465","deathDate":"","crematoriumName":"M.G.E.C.(T)","deceasedSex":"MALE","crematoriumCode":"","fatherName":"LATE KANAILAL GHOSH","regnNo":"","deathSite":"VIDYASAGAR S.G. HOSPITAL BEHALA KOL"},{"deceasedName":"SUPRITI RANJAN SARKAR","yearOfregistration":"2016","dateOfRegistration":"","deathRegnNo":"3466","deathDate":"","crematoriumName":"M.G.E.C.(T)","deceasedSex":"MALE","crematoriumCode":"","fatherName":"DR JIBAN KRISHNA SARKAR","regnNo":"","deathSite":""},{"deceasedName":"BISHAL RAM","yearOfregistration":"2016","dateOfRegistration":"","deathRegnNo":"3504","deathDate":"","crematoriumName":"M.G.E.C.(T)","deceasedSex":"MALE","crematoriumCode":"","fatherName":"S/O MADAN RAM","regnNo":"","deathSite":"S S K M HOSPITAL. KOLKATA"},{"deceasedName":"SAILEN SARKAR","yearOfregistration":"2016","dateOfRegistration":"","deathRegnNo":"24","deathDate":"","crematoriumName":"TALLYGUNGE CEMETERY","deceasedSex":"MALE","crematoriumCode":"","fatherName":"LATE BASANTA SARKAR","regnNo":"","deathSite":""},{"deceasedName":"PRATIMA BHATTACHARJEE","yearOfregistration":"2016","dateOfRegistration":"","deathRegnNo":"4844","deathDate":"","crematoriumName":"C.M.H.O. SPL. REGISTRATION","deceasedSex":"FEMALE","crematoriumCode":"","fatherName":"N.M","regnNo":"","deathSite":"M.C.HOSPITAL. KOL"},{"deceasedName":"MD.RIAZ","yearOfregistration":"2016","dateOfRegistration":"","deathRegnNo":"255","deathDate":"","crematoriumName":"SOLOAANA B.G.(T)","deceasedSex":"MALE","crematoriumCode":"","fatherName":"LATE MD.FAIYAZ","regnNo":"","deathSite":""},{"deceasedName":"NIRMAL KARMAKAR","yearOfregistration":"2016","dateOfRegistration":"","deathRegnNo":"3254","deathDate":"","crematoriumName":"C.M.H.O. SPL. REGISTRATION","deceasedSex":"MALE","crematoriumCode":"","fatherName":"LATE UMESH KARMAKAR","regnNo":"","deathSite":"KPC MEDICAL COLLEGE AND HOSPITAL,JADAVPUR"},{"deceasedName":"TARAPADA DAS","yearOfregistration":"2016","dateOfRegistration":"","deathRegnNo":"383","deathDate":"","crematoriumName":"N.B.G.(T)","deceasedSex":"MALE","crematoriumCode":"","fatherName":"S/O.LATE. SRI NIBAS DAS","regnNo":"","deathSite":""},{"deceasedName":"PURABI KAR ROY","yearOfregistration":"2016","dateOfRegistration":"","deathRegnNo":"3431","deathDate":"","crematoriumName":"M.G.E.C.(T)","deceasedSex":"FEMALE","crematoriumCode":"","fatherName":"N/A","regnNo":"","deathSite":""},{"deceasedName":"INDRA CHAND JOSHI","yearOfregistration":"2016","dateOfRegistration":"","deathRegnNo":"384","deathDate":"","crematoriumName":"N.B.G.(T)","deceasedSex":"MALE","crematoriumCode":"","fatherName":"S/O LATE CHANDI PRASAD JOSHI","regnNo":"","deathSite":"DIVINE NURSING  HOME PVT LTD. KOL"},{"deceasedName":"DULAL CHANDRA PAL","yearOfregistration":"2016","dateOfRegistration":"","deathRegnNo":"522","deathDate":"","crematoriumName":"C.B.G.(T)","deceasedSex":"MALE","crematoriumCode":"","fatherName":"LATE JOGENDRA KUMAR PAL","regnNo":"","deathSite":""},{"deceasedName":"GOUR MOHAN GHOSH","yearOfregistration":"2016","dateOfRegistration":"","deathRegnNo":"5019","deathDate":"","crematoriumName":"C.M.H.O. SPL. REGISTRATION","deceasedSex":"MALE","crematoriumCode":"","fatherName":"LATE FAKIR CHAND GHOSH","regnNo":"","deathSite":"S S K M HOSPITAL. KOLKATA"},{"deceasedName":"BHAGABAN DIN","yearOfregistration":"2016","dateOfRegistration":"","deathRegnNo":"3490","deathDate":"","crematoriumName":"M.G.E.C.(T)","deceasedSex":"MALE","crematoriumCode":"","fatherName":"LATE SITA RAM","regnNo":"","deathSite":""},{"deceasedName":"SMRITI CHAKRABORTY","yearOfregistration":"2016","dateOfRegistration":"","deathRegnNo":"3447","deathDate":"","crematoriumName":"M.G.E.C.(T)","deceasedSex":"FEMALE","crematoriumCode":"","fatherName":"N/A","regnNo":"","deathSite":"S S K M HOSPITAL. KOLKATA"},{"deceasedName":"KAMALA GHOSH","yearOfregistration":"2016","dateOfRegistration":"","deathRegnNo":"2522","deathDate":"","crematoriumName":"N.E.C.(T)","deceasedSex":"FEMALE","crematoriumCode":"","fatherName":"N/M","regnNo":"","deathSite":"I.D. AND B.G. HOSPITAL KOL-10"},{"deceasedName":"SAMIR DAS","yearOfregistration":"2016","dateOfRegistration":"","deathRegnNo":"2504","deathDate":"","crematoriumName":"N.E.C.(T)","deceasedSex":"MALE","crematoriumCode":"","fatherName":"S/O.LATE. NETAI CHANDRA DAS","regnNo":"","deathSite":""},{"deceasedName":"LALITA SARKAR","yearOfregistration":"2016","dateOfRegistration":"","deathRegnNo":"2507","deathDate":"","crematoriumName":"N.E.C.(T)","deceasedSex":"FEMALE","crematoriumCode":"","fatherName":"N/M","regnNo":"","deathSite":"B.R.SINGH HOSPITAL,KOLKATA"},{"deceasedName":"ANJALI DEY","yearOfregistration":"2016","dateOfRegistration":"","deathRegnNo":"2512","deathDate":"","crematoriumName":"N.E.C.(T)","deceasedSex":"FEMALE","crematoriumCode":"","fatherName":"N/M","regnNo":"","deathSite":""},{"deceasedName":"MAYA RANI SAHA","yearOfregistration":"2016","dateOfRegistration":"","deathRegnNo":"3471","deathDate":"","crematoriumName":"M.G.E.C.(T)","deceasedSex":"FEMALE","crematoriumCode":"","fatherName":"N/A","regnNo":"","deathSite":"SHANKARNATH DIALYSIS CENTRE & NURSING HOME.KOL-33"},{"deceasedName":"NABA KUMAR MISTRY","yearOfregistration":"2016","dateOfRegistration":"","deathRegnNo":"3113","deathDate":"","crematoriumName":"C.M.H.O. SPL. REGISTRATION","deceasedSex":"MALE","crematoriumCode":"","fatherName":"LT NEPAL CHANDRA MISTRY","regnNo":"","deathSite":"VIDYASAGAR S.G. HOSPITAL BEHALA KOL"},{"deceasedName":"LALITA DEVI","yearOfregistration":"2016","dateOfRegistration":"","deathRegnNo":"5088","deathDate":"","crematoriumName":"C.M.H.O. SPL. REGISTRATION","deceasedSex":"FEMALE","crematoriumCode":"","fatherName":"N.M","regnNo":"","deathSite":"APOLLO GLENEAGLES HOSPITAL KOL-54"},{"deceasedName":"BABY SHAISTA","yearOfregistration":"2016","dateOfRegistration":"","deathRegnNo":"432","deathDate":"","crematoriumName":"GOBRA B.G(T)","deceasedSex":"FEMALE","crematoriumCode":"","fatherName":"D/O MD MUSTAFA","regnNo":"","deathSite":""},{"deceasedName":"AMAL SINHA","yearOfregistration":"2016","dateOfRegistration":"","deathRegnNo":"2640","deathDate":"","crematoriumName":"N.E.C.(T)","deceasedSex":"MALE","crematoriumCode":"","fatherName":"LATE BANKIM CHANDRA SINHA","regnNo":"","deathSite":"NORTH CITY HOSP.AND NEURO INST. PVT.LTD.,KOL"},{"deceasedName":"SAMBHU NATH MUKHERJEE","yearOfregistration":"2016","dateOfRegistration":"","deathRegnNo":"4617","deathDate":"","crematoriumName":"C.M.H.O. SPL. REGISTRATION","deceasedSex":"MALE","crematoriumCode":"","fatherName":"LATE JAMINI BHUSAN MUKHERJEE","regnNo":"","deathSite":"A.M.R.I. HOSPITAL,DHAKURIA,KOLKATA 700029"},{"deceasedName":"TAPAN KHETRI","yearOfregistration":"2016","dateOfRegistration":"","deathRegnNo":"2488","deathDate":"","crematoriumName":"N.E.C.(T)","deceasedSex":"MALE","crematoriumCode":"","fatherName":"LT. SITARAM KHETRI","regnNo":"","deathSite":""},{"deceasedName":"DIPTY CHATTERJEE","yearOfregistration":"2016","dateOfRegistration":"","deathRegnNo":"2502","deathDate":"","crematoriumName":"N.E.C.(T)","deceasedSex":"FEMALE","crematoriumCode":"","fatherName":"N/M","regnNo":"","deathSite":"S.V.S. MARWARI HOSPITAL,KOLKATA 700009"},{"deceasedName":"JHUMA DEVI","yearOfregistration":"2016","dateOfRegistration":"","deathRegnNo":"3463","deathDate":"","crematoriumName":"M.G.E.C.(T)","deceasedSex":"FEMALE","crematoriumCode":"","fatherName":"N/A","regnNo":"","deathSite":"C.N.M.C AND HOSPITAL, KOLKATA-700014"},{"deceasedName":"RAMU AMMAL @ RAMA LAKSHMI","yearOfregistration":"2016","dateOfRegistration":"","deathRegnNo":"530","deathDate":"","crematoriumName":"SIRITY B. GHAT E. (T)","deceasedSex":"FEMALE","crematoriumCode":"","fatherName":"NM","regnNo":"","deathSite":""},{"deceasedName":"CHANDESHWAR RAY","yearOfregistration":"2016","dateOfRegistration":"","deathRegnNo":"2506","deathDate":"","crematoriumName":"N.E.C.(T)","deceasedSex":"MALE","crematoriumCode":"","fatherName":"S/O. SHEWCHAND RAY","regnNo":"","deathSite":"KHANNA NURSING HOME"},{"deceasedName":"PHANI BHUSAN BHATTACHARJEE","yearOfregistration":"2016","dateOfRegistration":"","deathRegnNo":"3451","deathDate":"","crematoriumName":"M.G.E.C.(T)","deceasedSex":"MALE","crematoriumCode":"","fatherName":"LATE MADHUSUDAN BHATTACHARJEE","regnNo":"","deathSite":""},{"deceasedName":"RANU SARKAR","yearOfregistration":"2016","dateOfRegistration":"","deathRegnNo":"3453","deathDate":"","crematoriumName":"M.G.E.C.(T)","deceasedSex":"FEMALE","crematoriumCode":"","fatherName":"N/A","regnNo":"","deathSite":"APOLLO GLENEAGLES HOSPITAL KOL-54"},{"deceasedName":"RABI KHALKO","yearOfregistration":"2016","dateOfRegistration":"","deathRegnNo":"527","deathDate":"","crematoriumName":"SIRITY B. GHAT E. (T)","deceasedSex":"MALE","crematoriumCode":"","fatherName":"LATE KALI KHALKO","regnNo":"","deathSite":"CALCUTTA NATIONAL MEDICAL COLLEGE AND HOSP."},{"deceasedName":"SANKARI DAS","yearOfregistration":"2016","dateOfRegistration":"","deathRegnNo":"91","deathDate":"","crematoriumName":"MURARIPUKUR B.G. (T)","deceasedSex":"FEMALE","crematoriumCode":"","fatherName":"SANJAY DAS","regnNo":"","deathSite":""},{"deceasedName":"RIPA CHATTERJEE","yearOfregistration":"2016","dateOfRegistration":"","deathRegnNo":"3542","deathDate":"","crematoriumName":"M.G.E.C.(T)","deceasedSex":"FEMALE","crematoriumCode":"","fatherName":"N/A","regnNo":"","deathSite":""},{"deceasedName":"RAM NARESH SHA","yearOfregistration":"2016","dateOfRegistration":"","deathRegnNo":"2561","deathDate":"","crematoriumName":"N.E.C.(T)","deceasedSex":"MALE","crematoriumCode":"","fatherName":"S/O LT RAMBILASH SHA","regnNo":"","deathSite":"N R S MEDICAL COLLEGE AND HOSPITAL. KOLKATA-14"},{"deceasedName":"SUKUMAR BACHAR","yearOfregistration":"2016","dateOfRegistration":"","deathRegnNo":"3449","deathDate":"","crematoriumName":"M.G.E.C.(T)","deceasedSex":"MALE","crematoriumCode":"","fatherName":"LATE DEBENDRA NATH BACHAR","regnNo":"","deathSite":"CHITTARANJAN NATIONAL CANCER INSTITUTE"},{"deceasedName":"SISIR SAHA","yearOfregistration":"2016","dateOfRegistration":"","deathRegnNo":"528","deathDate":"","crematoriumName":"SIRITY B. GHAT E. (T)","deceasedSex":"MALE","crematoriumCode":"","fatherName":"LATE SATISH CHANDRA SAHA","regnNo":"","deathSite":"SAROJ GUPTA CANCER CENTRE&RESEARCH INSTITUTE.KOL-63"},{"deceasedName":"MANJUSREE NATH","yearOfregistration":"2016","dateOfRegistration":"","deathRegnNo":"3432","deathDate":"","crematoriumName":"M.G.E.C.(T)","deceasedSex":"FEMALE","crematoriumCode":"","fatherName":"N/A","regnNo":"","deathSite":""},{"deceasedName":"SAIFUDDIN BADRI ALIAS SAHABADDIN BODDI","yearOfregistration":"2016","dateOfRegistration":"","deathRegnNo":"4606","deathDate":"","crematoriumName":"C.M.H.O. SPL. REGISTRATION","deceasedSex":"MALE","crematoriumCode":"","fatherName":"SAHAR ALI BODDI","regnNo":"","deathSite":"R G KAR MEDICAL COLLEGE AND HOSPITAL KOL"},{"deceasedName":"SACHINDRA CHANDRA SARKAR","yearOfregistration":"2016","dateOfRegistration":"","deathRegnNo":"5164","deathDate":"","crematoriumName":"C.M.H.O. SPL. REGISTRATION","deceasedSex":"MALE","crematoriumCode":"","fatherName":"LT HARENDRA CHANDRA SARKAR","regnNo":"","deathSite":"N R S MEDICAL COLLEGE AND HOSPITAL. KOLKATA-14"},{"deceasedName":"RITWIKA MUKHERJEE","yearOfregistration":"2016","dateOfRegistration":"","deathRegnNo":"672","deathDate":"","crematoriumName":"GARIA B.G.(T)","deceasedSex":"FEMALE","crematoriumCode":"","fatherName":"N/M","regnNo":"","deathSite":"PEERLESS HOSPITEX HOSPITAL AND RESEARCH CENTER LIMITED, KOLKATA-94."},{"deceasedName":"SUBIR KUMAR DAS","yearOfregistration":"2016","dateOfRegistration":"","deathRegnNo":"2501","deathDate":"","crematoriumName":"N.E.C.(T)","deceasedSex":"MALE","crematoriumCode":"","fatherName":"LATE. BIDHU BHUSHAN DAS","regnNo":"","deathSite":"APOLLO GLENEAGLES HOSPITAL KOL-54"},{"deceasedName":"NARAYAN MUKHERJEE","yearOfregistration":"2016","dateOfRegistration":"","deathRegnNo":"181","deathDate":"","crematoriumName":"K.M.B.G.(T)","deceasedSex":"MALE","crematoriumCode":"","fatherName":"LATE G. S. MUKHERJEE ALIAS GOUR SHANKAR MUKHERJEE","regnNo":"","deathSite":"MEDICAL COLLEGE AND HOSPITAL,KOLKATA 73"},{"deceasedName":"BISWAJIT DEBNATH","yearOfregistration":"2016","dateOfRegistration":"","deathRegnNo":"3428","deathDate":"","crematoriumName":"M.G.E.C.(T)","deceasedSex":"MALE","crematoriumCode":"","fatherName":"LATE RADHAKANTA DEBNATH","regnNo":"","deathSite":"THE CALCUTTA MEDICAL RESEARCH INSTITUTE, KOLKATA-27"},{"deceasedName":"AJIT HALDER","yearOfregistration":"2016","dateOfRegistration":"","deathRegnNo":"3444","deathDate":"","crematoriumName":"M.G.E.C.(T)","deceasedSex":"MALE","crematoriumCode":"","fatherName":"LATE ANANTA HALDER","regnNo":"","deathSite":"SAROJ GUPTA CANCER CENTRE&RESEARCH INSTITUTE.KOL-63"},{"deceasedName":"TAPAN KUMAR MUKHERJEE","yearOfregistration":"2016","dateOfRegistration":"","deathRegnNo":"523","deathDate":"","crematoriumName":"C.B.G.(T)","deceasedSex":"MALE","crematoriumCode":"","fatherName":"LATE S.C. MUKHERJEE","regnNo":"","deathSite":"MEDICA SUPERSPECIALTY HOSPITAL.KOL 99"},{"deceasedName":"GOPAL DAS SHARMA","yearOfregistration":"2016","dateOfRegistration":"","deathRegnNo":"5253","deathDate":"","crematoriumName":"C.M.H.O. SPL. REGISTRATION","deceasedSex":"MALE","crematoriumCode":"","fatherName":"LATE HARENDRA NATH DAS SHARMA","regnNo":"","deathSite":"S S K M HOSPITAL. KOLKATA"},{"deceasedName":"NIRMAL KANTI BHATTACHARJEE","yearOfregistration":"2016","dateOfRegistration":"","deathRegnNo":"5451","deathDate":"","crematoriumName":"C.M.H.O. SPL. REGISTRATION","deceasedSex":"MALE","crematoriumCode":"","fatherName":"LATE ASUTOSH BHATTACHARJEE","regnNo":"","deathSite":"ESKAG SANJEEVANI PVT. LTD."},{"deceasedName":"BHIKHARI SHAW","yearOfregistration":"2016","dateOfRegistration":"","deathRegnNo":"6485","deathDate":"","crematoriumName":"C.M.H.O. SPL. REGISTRATION","deceasedSex":"MALE","crematoriumCode":"","fatherName":"LT BISWANATH SHAW","regnNo":"","deathSite":"R G KAR MEDICAL COLLEGE AND HOSPITAL KOL"},{"deceasedName":"MURLI HARIJAN","yearOfregistration":"2016","dateOfRegistration":"","deathRegnNo":"4476","deathDate":"","crematoriumName":"C.M.H.O. SPL. REGISTRATION","deceasedSex":"MALE","crematoriumCode":"","fatherName":"LATE KANAHI HARIJAN","regnNo":"","deathSite":"RUBY GENERAL HOSPITAL KOLKATA"},{"deceasedName":"AMAL MONDAL","yearOfregistration":"2016","dateOfRegistration":"","deathRegnNo":"2495","deathDate":"","crematoriumName":"N.E.C.(T)","deceasedSex":"MALE","crematoriumCode":"","fatherName":"LATE HAZARILAL MONDAL","regnNo":"","deathSite":"DIVINE NURSING  HOME PVT LTD. KOL"},{"deceasedName":"SWARAJ BHADRA","yearOfregistration":"2016","dateOfRegistration":"","deathRegnNo":"2499","deathDate":"","crematoriumName":"N.E.C.(T)","deceasedSex":"MALE","crematoriumCode":"","fatherName":"S/O.LATE. KHITISH CH. BHADRA","regnNo":"","deathSite":"R G KAR MEDICAL COLLEGE AND HOSPITAL KOL"},{"deceasedName":"RAM NARAYAN CHATTERJEE","yearOfregistration":"2016","dateOfRegistration":"","deathRegnNo":"3583","deathDate":"","crematoriumName":"M.G.E.C.(T)","deceasedSex":"MALE","crematoriumCode":"","fatherName":"LATE SHYAMAPADA CHATTERJEE","regnNo":"","deathSite":""},{"deceasedName":"SANKAR SAHA","yearOfregistration":"2016","dateOfRegistration":"","deathRegnNo":"2516","deathDate":"","crematoriumName":"N.E.C.(T)","deceasedSex":"MALE","crematoriumCode":"","fatherName":"S/O.LATE. HARIDAS SAHA","regnNo":"","deathSite":"NABA JIBAN HOSPITAL PVT LTD,KOL'700004"},{"deceasedName":"ARVIND KHAITAN","yearOfregistration":"2016","dateOfRegistration":"","deathRegnNo":"382","deathDate":"","crematoriumName":"N.B.G.(T)","deceasedSex":"MALE","crematoriumCode":"","fatherName":"LATE M.L. KHAITAN","regnNo":"","deathSite":"MEDICA SUPERSPECIALTY HOSPITAL.KOL 99"},{"deceasedName":"SUSHIL CHANDRA SARDAR","yearOfregistration":"2016","dateOfRegistration":"","deathRegnNo":"669","deathDate":"","crematoriumName":"GARIA B.G.(T)","deceasedSex":"MALE","crematoriumCode":"","fatherName":"LATE NAREN CHANDRA SARDAR","regnNo":"","deathSite":""},{"deceasedName":"JAGADISH GOSWAMI","yearOfregistration":"2016","dateOfRegistration":"","deathRegnNo":"4599","deathDate":"","crematoriumName":"C.M.H.O. SPL. REGISTRATION","deceasedSex":"MALE","crematoriumCode":"","fatherName":"LATE NARENDRA NATH GOSWAMI","regnNo":"","deathSite":"COMMAND HOSPITAL (E.C.) KOL"},{"deceasedName":"ZAITUN ABBAS MORUDWALA","yearOfregistration":"2016","dateOfRegistration":"","deathRegnNo":"4","deathDate":"","crematoriumName":"BAG E MD. (P) B.G.","deceasedSex":"FEMALE","crematoriumCode":"","fatherName":"N.M","regnNo":"","deathSite":"RUBY GENERAL HOSPITAL KOLKATA"},{"deceasedName":"SUBRATA RUDRA","yearOfregistration":"2016","dateOfRegistration":"","deathRegnNo":"3429","deathDate":"","crematoriumName":"M.G.E.C.(T)","deceasedSex":"MALE","crematoriumCode":"","fatherName":"LATE SUNIL KUMAR RUDRA","regnNo":"","deathSite":"AMRI HOSPITALS  KOLKATA 700029"},{"deceasedName":"BISHNU DEV","yearOfregistration":"2016","dateOfRegistration":"","deathRegnNo":"640","deathDate":"","crematoriumName":"SIRITY B. GHAT E. (T)","deceasedSex":"MALE","crematoriumCode":"","fatherName":"NM","regnNo":"","deathSite":"VIDYASAGAR S.G. HOSPITAL BEHALA KOL"},{"deceasedName":"MINATI ROY CHOWDHURY","yearOfregistration":"2016","dateOfRegistration":"","deathRegnNo":"3454","deathDate":"","crematoriumName":"M.G.E.C.(T)","deceasedSex":"FEMALE","crematoriumCode":"","fatherName":"N/A","regnNo":"","deathSite":""},{"deceasedName":"SUBHASIS GHOSH","yearOfregistration":"2016","dateOfRegistration":"","deathRegnNo":"3480","deathDate":"","crematoriumName":"M.G.E.C.(T)","deceasedSex":"MALE","crematoriumCode":"","fatherName":"NRIPENDRA KUMAR GHOSH","regnNo":"","deathSite":"COMMAND HOSPITAL (E.C.) KOL"},{"deceasedName":"SANTI LATA DAS","yearOfregistration":"2016","dateOfRegistration":"","deathRegnNo":"2521","deathDate":"","crematoriumName":"N.E.C.(T)","deceasedSex":"FEMALE","crematoriumCode":"","fatherName":"N/M","regnNo":"","deathSite":""},{"deceasedName":"PALY BANERJEE","yearOfregistration":"2016","dateOfRegistration":"","deathRegnNo":"3455","deathDate":"","crematoriumName":"M.G.E.C.(T)","deceasedSex":"FEMALE","crematoriumCode":"","fatherName":"N/A","regnNo":"","deathSite":"KPC MEDICAL COLLEGE AND HOSPITAL,JADAVPUR"},{"deceasedName":"MD.YASIN","yearOfregistration":"2016","dateOfRegistration":"","deathRegnNo":"258","deathDate":"","crematoriumName":"SOLOAANA B.G.(T)","deceasedSex":"MALE","crematoriumCode":"","fatherName":"LATE HAWALDAR KHAN","regnNo":"","deathSite":"SAROJ GUPTA CANCER CENTRE&RESEARCH INSTITUTE.KOL-63"},{"deceasedName":"RAJENDRA SINGH","yearOfregistration":"2016","dateOfRegistration":"","deathRegnNo":"5432","deathDate":"","crematoriumName":"C.M.H.O. SPL. REGISTRATION","deceasedSex":"MALE","crematoriumCode":"","fatherName":"HEMNARAYAN SINGH","regnNo":"","deathSite":"APOLLO GLENEAGLES HOSPITAL KOL-54"},{"deceasedName":"ABHAMOYEE HAZRA","yearOfregistration":"2016","dateOfRegistration":"","deathRegnNo":"3434","deathDate":"","crematoriumName":"M.G.E.C.(T)","deceasedSex":"FEMALE","crematoriumCode":"","fatherName":"N/A","regnNo":"","deathSite":""},{"deceasedName":"SK. RIYASUDDIN","yearOfregistration":"2016","dateOfRegistration":"","deathRegnNo":"4508","deathDate":"","crematoriumName":"C.M.H.O. SPL. REGISTRATION","deceasedSex":"MALE","crematoriumCode":"","fatherName":"LATE SK. ALAM","regnNo":"","deathSite":"S S K M HOSPITAL. KOLKATA"},{"deceasedName":"DR.KALYANI MUKHOPADHYAY","yearOfregistration":"2016","dateOfRegistration":"","deathRegnNo":"6126","deathDate":"","crematoriumName":"C.M.H.O. SPL. REGISTRATION","deceasedSex":"FEMALE","crematoriumCode":"","fatherName":"N.M","regnNo":"","deathSite":"BELLE VUE CLINIC KOLKATA"},{"deceasedName":"SAIRA KHATOON","yearOfregistration":"2016","dateOfRegistration":"","deathRegnNo":"132","deathDate":"","crematoriumName":"BAGMARI B.G. (T)","deceasedSex":"FEMALE","crematoriumCode":"","fatherName":"------------N/M------------","regnNo":"","deathSite":"N R S MEDICAL COLLEGE AND HOSPITAL. KOLKATA-14"},{"deceasedName":"MD.ASLAM","yearOfregistration":"2016","dateOfRegistration":"","deathRegnNo":"257","deathDate":"","crematoriumName":"SOLOAANA B.G.(T)","deceasedSex":"MALE","crematoriumCode":"","fatherName":"LATE MD.CHHOTU","regnNo":"","deathSite":"BELLONA NURSING HOME AND D.C. KOL"},{"deceasedName":"JHARNA DASGUPTA","yearOfregistration":"2016","dateOfRegistration":"","deathRegnNo":"3446","deathDate":"","crematoriumName":"M.G.E.C.(T)","deceasedSex":"FEMALE","crematoriumCode":"","fatherName":"LATE GIRIJA PRASANNA DASGUPTA","regnNo":"","deathSite":"M R BANGUR HOSPITAL,KOLKATA 700033"},{"deceasedName":"ANTIKA GHOSH","yearOfregistration":"2016","dateOfRegistration":"","deathRegnNo":"2497","deathDate":"","crematoriumName":"N.E.C.(T)","deceasedSex":"FEMALE","crematoriumCode":"","fatherName":"N/M","regnNo":"","deathSite":"R G KAR MEDICAL COLLEGE AND HOSPITAL KOL"},{"deceasedName":"KALYAN KUMAR RAYCHAUDHURI","yearOfregistration":"2016","dateOfRegistration":"","deathRegnNo":"1040","deathDate":"","crematoriumName":"SIRITY B. GHAT E. (T)","deceasedSex":"MALE","crematoriumCode":"","fatherName":"LATE BIBHUTI BHUSAN RAYCHAUDHURI","regnNo":"","deathSite":""},{"deceasedName":"PARIMAL SARDAR","yearOfregistration":"2016","dateOfRegistration":"","deathRegnNo":"6327","deathDate":"","crematoriumName":"C.M.H.O. SPL. REGISTRATION","deceasedSex":"MALE","crematoriumCode":"","fatherName":"LATE MULUK CHAND SARDAR","regnNo":"","deathSite":"R G KAR MEDICAL COLLEGE AND HOSPITAL KOL"},{"deceasedName":"SANGITA AGARWAL","yearOfregistration":"2016","dateOfRegistration":"","deathRegnNo":"379","deathDate":"","crematoriumName":"N.B.G.(T)","deceasedSex":"FEMALE","crematoriumCode":"","fatherName":"N/M","regnNo":"","deathSite":"MARWARI  RELIEF SOCIETY HOSPITAL, KOL-7"},{"deceasedName":"AJIT KUMAR MAITY","yearOfregistration":"2016","dateOfRegistration":"","deathRegnNo":"3824","deathDate":"","crematoriumName":"C.M.H.O. SPL. REGISTRATION","deceasedSex":"MALE","crematoriumCode":"","fatherName":"LATE ISWAR MAITY","regnNo":"","deathSite":"MEDICA SUPERSPECIALTY HOSPITAL.KOL 99"},{"deceasedName":"SUBHAS CHANDRA GAINE","yearOfregistration":"2016","dateOfRegistration":"","deathRegnNo":"3433","deathDate":"","crematoriumName":"M.G.E.C.(T)","deceasedSex":"MALE","crematoriumCode":"","fatherName":"LATE CHARU CHANDRA GAINE","regnNo":"","deathSite":""},{"deceasedName":"ALO SARKAR","yearOfregistration":"2016","dateOfRegistration":"","deathRegnNo":"3909","deathDate":"","crematoriumName":"C.M.H.O. SPL. REGISTRATION","deceasedSex":"FEMALE","crematoriumCode":"","fatherName":"N.M","regnNo":"","deathSite":"APOLLO GLENEAGLES HOSPITAL KOL-54"},{"deceasedName":"MUNSI ABU BAKKAR","yearOfregistration":"2016","dateOfRegistration":"","deathRegnNo":"4026","deathDate":"","crematoriumName":"C.M.H.O. SPL. REGISTRATION","deceasedSex":"MALE","crematoriumCode":"","fatherName":"MUNSI IBRAHIM","regnNo":"","deathSite":"COMMAND HOSPITAL (E.C.) KOL"},{"deceasedName":"AJIJUL MOLLICK","yearOfregistration":"2016","dateOfRegistration":"","deathRegnNo":"4279","deathDate":"","crematoriumName":"C.M.H.O. SPL. REGISTRATION","deceasedSex":"MALE","crematoriumCode":"","fatherName":"LT MAJAHAR MOLLICK","regnNo":"","deathSite":"E.S.I. HOSPITAL,MANICKTALA,KOLKATA-54"},{"deceasedName":"CHAMPA PASWAN","yearOfregistration":"2016","dateOfRegistration":"","deathRegnNo":"3459","deathDate":"","crematoriumName":"M.G.E.C.(T)","deceasedSex":"FEMALE","crematoriumCode":"","fatherName":"N/A","regnNo":"","deathSite":""},{"deceasedName":"KARTICK ROY","yearOfregistration":"2016","dateOfRegistration":"","deathRegnNo":"2513","deathDate":"","crematoriumName":"N.E.C.(T)","deceasedSex":"MALE","crematoriumCode":"","fatherName":"LATE KRISHNA ROY","regnNo":"","deathSite":"R G KAR MEDICAL COLLEGE AND HOSPITAL KOL"},{"deceasedName":"GURUPADA POREY","yearOfregistration":"2016","dateOfRegistration":"","deathRegnNo":"2498","deathDate":"","crematoriumName":"N.E.C.(T)","deceasedSex":"MALE","crematoriumCode":"","fatherName":"S/O.LATE. JUGAL POREY","regnNo":"","deathSite":"R G KAR MEDICAL COLLEGE AND HOSPITAL KOL"},{"deceasedName":"GIRDHAR LAL","yearOfregistration":"2016","dateOfRegistration":"","deathRegnNo":"2514","deathDate":"","crematoriumName":"N.E.C.(T)","deceasedSex":"MALE","crematoriumCode":"","fatherName":"S/O. HATHI RAM","regnNo":"","deathSite":"S.V.S. MARWARI HOSPITAL,KOLKATA 700009"},{"deceasedName":"SHIV PRASAD","yearOfregistration":"2016","dateOfRegistration":"","deathRegnNo":"19","deathDate":"","crematoriumName":"M.G.E.C.(T) UNCLAIMED","deceasedSex":"MALE","crematoriumCode":"","fatherName":"N/A","regnNo":"","deathSite":"NIRMAL HRIDAY HOME"},{"deceasedName":"BELA MUKHERJEE","yearOfregistration":"2016","dateOfRegistration":"","deathRegnNo":"3462","deathDate":"","crematoriumName":"M.G.E.C.(T)","deceasedSex":"FEMALE","crematoriumCode":"","fatherName":"N/A","regnNo":"","deathSite":""},{"deceasedName":"GOUR HAZRA","yearOfregistration":"2016","dateOfRegistration":"","deathRegnNo":"529","deathDate":"","crematoriumName":"SIRITY B. GHAT E. (T)","deceasedSex":"MALE","crematoriumCode":"","fatherName":"GOPAL HAZRA","regnNo":"","deathSite":"C.N.M.C AND HOSPITAL, KOLKATA-700014"},{"deceasedName":"MOTILAL SAHANI","yearOfregistration":"2016","dateOfRegistration":"","deathRegnNo":"2527","deathDate":"","crematoriumName":"N.E.C.(T)","deceasedSex":"MALE","crematoriumCode":"","fatherName":"S/O LATE RITLAL SAHANI","regnNo":"","deathSite":""},{"deceasedName":"RAJESWARI RANA","yearOfregistration":"2016","dateOfRegistration":"","deathRegnNo":"3479","deathDate":"","crematoriumName":"M.G.E.C.(T)","deceasedSex":"FEMALE","crematoriumCode":"","fatherName":"N/A","regnNo":"","deathSite":"VIDYASAGAR S.G. HOSPITAL BEHALA KOL"},{"deceasedName":"KEYA BANERJEE","yearOfregistration":"2016","dateOfRegistration":"","deathRegnNo":"3500","deathDate":"","crematoriumName":"M.G.E.C.(T)","deceasedSex":"FEMALE","crematoriumCode":"","fatherName":"N/M","regnNo":"","deathSite":"KPC MEDICAL COLLEGE AND HOSPITAL,JADAVPUR"},{"deceasedName":"SAMBHUNATH PARUI","yearOfregistration":"2016","dateOfRegistration":"","deathRegnNo":"3458","deathDate":"","crematoriumName":"M.G.E.C.(T)","deceasedSex":"MALE","crematoriumCode":"","fatherName":"LATE DHIRENDRANATH PARUI","regnNo":"","deathSite":"REPOSE CLINIC AND RESEARCH CENTRE PVT.LTD.,KOLKATA 19"},{"deceasedName":"CHANDRIMA HALDER","yearOfregistration":"2016","dateOfRegistration":"","deathRegnNo":"3468","deathDate":"","crematoriumName":"M.G.E.C.(T)","deceasedSex":"FEMALE","crematoriumCode":"","fatherName":"N/A","regnNo":"","deathSite":"SAROJ GUPTA CANCER CENTRE&RESEARCH INSTITUTE.KOL-63"},{"deceasedName":"REKHA GUPTA","yearOfregistration":"2016","dateOfRegistration":"","deathRegnNo":"2529","deathDate":"","crematoriumName":"N.E.C.(T)","deceasedSex":"FEMALE","crematoriumCode":"","fatherName":"N/M","regnNo":"","deathSite":"APEX NURSING HOME"},{"deceasedName":"SHIB SUNDAR CHOWDHURY","yearOfregistration":"2016","dateOfRegistration":"","deathRegnNo":"2496","deathDate":"","crematoriumName":"N.E.C.(T)","deceasedSex":"MALE","crematoriumCode":"","fatherName":"S/O.LATE. PANCHKARI CHOWDHURY","regnNo":"","deathSite":"SUNFLOWER  NURSING  HOME"},{"deceasedName":"JANKI DAS MUNDHRA","yearOfregistration":"2016","dateOfRegistration":"","deathRegnNo":"381","deathDate":"","crematoriumName":"N.B.G.(T)","deceasedSex":"MALE","crematoriumCode":"","fatherName":"LATE HAR DAS MUNDHRA","regnNo":"","deathSite":"WOODLANDS MULTISPECIALITY HOSP.LTD."},{"deceasedName":"KANHAIYA LAL JAIN","yearOfregistration":"2016","dateOfRegistration":"","deathRegnNo":"380","deathDate":"","crematoriumName":"N.B.G.(T)","deceasedSex":"MALE","crematoriumCode":"","fatherName":"LATE MEGHRAJ JI JAIN PUGALIA","regnNo":"","deathSite":"WOODLANDS MULTISPECIALITY HOSP.LTD."},{"deceasedName":"KESRI DEVI GUPTA","yearOfregistration":"2016","dateOfRegistration":"","deathRegnNo":"378","deathDate":"","crematoriumName":"N.B.G.(T)","deceasedSex":"FEMALE","crematoriumCode":"","fatherName":"N/M","regnNo":"","deathSite":""},{"deceasedName":"MINU DAS","yearOfregistration":"2016","dateOfRegistration":"","deathRegnNo":"526","deathDate":"","crematoriumName":"SIRITY B. GHAT E. (T)","deceasedSex":"FEMALE","crematoriumCode":"","fatherName":"LATE MADHAB CHANDRA DAS","regnNo":"","deathSite":""},{"deceasedName":"SUSHEN CHANDRA SEN","yearOfregistration":"2016","dateOfRegistration":"","deathRegnNo":"3472","deathDate":"","crematoriumName":"M.G.E.C.(T)","deceasedSex":"MALE","crematoriumCode":"","fatherName":"LATE DINO NATH SEN","regnNo":"","deathSite":""},{"deceasedName":"SUTINDER SINGH DHINGRA","yearOfregistration":"2016","dateOfRegistration":"","deathRegnNo":"3438","deathDate":"","crematoriumName":"M.G.E.C.(T)","deceasedSex":"MALE","crematoriumCode":"","fatherName":"N/A","regnNo":"","deathSite":""},{"deceasedName":"NEONATAL BABY(KUMARI).","yearOfregistration":"2016","dateOfRegistration":"","deathRegnNo":"207","deathDate":"","crematoriumName":"TOPSIA HINDU B.G.(T)","deceasedSex":"FEMALE","crematoriumCode":"","fatherName":"LAXAMAN KR. RAM","regnNo":"","deathSite":""},{"deceasedName":"SANTI PROSANNA CHATTERJEE","yearOfregistration":"2016","dateOfRegistration":"","deathRegnNo":"2541","deathDate":"","crematoriumName":"N.E.C.(T)","deceasedSex":"MALE","crematoriumCode":"","fatherName":"N/M","regnNo":"","deathSite":""},{"deceasedName":"RAHANA BIBI","yearOfregistration":"2016","dateOfRegistration":"","deathRegnNo":"433","deathDate":"","crematoriumName":"GOBRA B.G(T)","deceasedSex":"FEMALE","crematoriumCode":"","fatherName":"------N/M-----","regnNo":"","deathSite":""},{"deceasedName":"PUSPA KARMAKAR","yearOfregistration":"2016","dateOfRegistration":"","deathRegnNo":"2510","deathDate":"","crematoriumName":"N.E.C.(T)","deceasedSex":"FEMALE","crematoriumCode":"","fatherName":"N/M","regnNo":"","deathSite":"R G KAR MEDICAL COLLEGE AND HOSPITAL KOL"},{"deceasedName":"ARPITA SINHA","yearOfregistration":"2016","dateOfRegistration":"","deathRegnNo":"3425","deathDate":"","crematoriumName":"M.G.E.C.(T)","deceasedSex":"FEMALE","crematoriumCode":"","fatherName":"N/M","regnNo":"","deathSite":"A.M.R.I. HOSPITAL,DHAKURIA,KOLKATA 700029"},{"deceasedName":"CHINTAMANI SARKAR","yearOfregistration":"2016","dateOfRegistration":"","deathRegnNo":"3456","deathDate":"","crematoriumName":"M.G.E.C.(T)","deceasedSex":"FEMALE","crematoriumCode":"","fatherName":"N/A","regnNo":"","deathSite":""},{"deceasedName":"MINU RANI SIL","yearOfregistration":"2016","dateOfRegistration":"","deathRegnNo":"2515","deathDate":"","crematoriumName":"N.E.C.(T)","deceasedSex":"FEMALE","crematoriumCode":"","fatherName":"N/M","regnNo":"","deathSite":""},{"deceasedName":"BISWANATH HALDER","yearOfregistration":"2016","dateOfRegistration":"","deathRegnNo":"3478","deathDate":"","crematoriumName":"M.G.E.C.(T)","deceasedSex":"MALE","crematoriumCode":"","fatherName":"LATE HARIPODDO HALDER","regnNo":"","deathSite":"S S K M HOSPITAL. KOLKATA"},{"deceasedName":"SURESH SINGH","yearOfregistration":"2016","dateOfRegistration":"","deathRegnNo":"3629","deathDate":"","crematoriumName":"C.M.H.O. SPL. REGISTRATION","deceasedSex":"MALE","crematoriumCode":"","fatherName":"LATE RAM JATAN SINGH","regnNo":"","deathSite":"S S K M HOSPITAL. KOLKATA"},{"deceasedName":"JYOTSNA BODAK","yearOfregistration":"2016","dateOfRegistration":"","deathRegnNo":"3666","deathDate":"","crematoriumName":"C.M.H.O. SPL. REGISTRATION","deceasedSex":"FEMALE","crematoriumCode":"","fatherName":"N.M","regnNo":"","deathSite":"M.C.HOSPITAL. KOL"},{"deceasedName":"MARY BRAMBLEBEE","yearOfregistration":"2016","dateOfRegistration":"","deathRegnNo":"16","deathDate":"","crematoriumName":"BHAWANIPUR CEMETERY","deceasedSex":"FEMALE","crematoriumCode":"","fatherName":"----------------------N/M-----------------","regnNo":"","deathSite":"THE CALCUTTA MEDICAL RESEARCH INSTITUTE, KOLKATA-27"},{"deceasedName":"GANESH CHANDRA SINGHA","yearOfregistration":"2016","dateOfRegistration":"","deathRegnNo":"3617","deathDate":"","crematoriumName":"C.M.H.O. SPL. REGISTRATION","deceasedSex":"MALE","crematoriumCode":"","fatherName":"LATE S.R.SINGHA","regnNo":"","deathSite":""},{"deceasedName":"PRABHASH KOLEY","yearOfregistration":"2016","dateOfRegistration":"","deathRegnNo":"3367","deathDate":"","crematoriumName":"C.M.H.O. SPL. REGISTRATION","deceasedSex":"MALE","crematoriumCode":"","fatherName":"LATE BHOLANATH KOLEY","regnNo":"","deathSite":"M.C.HOSPITAL. KOL"},{"deceasedName":"BIJALI ROY","yearOfregistration":"2016","dateOfRegistration":"","deathRegnNo":"3770","deathDate":"","crematoriumName":"C.M.H.O. SPL. REGISTRATION","deceasedSex":"FEMALE","crematoriumCode":"","fatherName":"N.M","regnNo":"","deathSite":"B.R.SINGH HOSPITAL,KOLKATA"},{"deceasedName":"TAPATI DUTTA","yearOfregistration":"2016","dateOfRegistration":"","deathRegnNo":"2490","deathDate":"","crematoriumName":"N.E.C.(T)","deceasedSex":"FEMALE","crematoriumCode":"","fatherName":"N/M","regnNo":"","deathSite":""},{"deceasedName":"SHYAMAL MITRA","yearOfregistration":"2016","dateOfRegistration":"","deathRegnNo":"3439","deathDate":"","crematoriumName":"M.G.E.C.(T)","deceasedSex":"MALE","crematoriumCode":"","fatherName":"S/O LATE JYOTISH CH. MITRA","regnNo":"","deathSite":""},{"deceasedName":"MIRA MANDAL","yearOfregistration":"2016","dateOfRegistration":"","deathRegnNo":"3705","deathDate":"","crematoriumName":"C.M.H.O. SPL. REGISTRATION","deceasedSex":"FEMALE","crematoriumCode":"","fatherName":"----------------------N/M-----------------","regnNo":"","deathSite":"S S K M HOSPITAL. KOLKATA"},{"deceasedName":"DEBDAS KARMAKAR","yearOfregistration":"2016","dateOfRegistration":"","deathRegnNo":"520","deathDate":"","crematoriumName":"C.B.G.(T)","deceasedSex":"MALE","crematoriumCode":"","fatherName":"S/O-LATE P.C.KARMAKAR","regnNo":"","deathSite":"R G KAR MEDICAL COLLEGE AND HOSPITAL KOL"},{"deceasedName":"DILIP KUMAR DAS","yearOfregistration":"2016","dateOfRegistration":"","deathRegnNo":"4025","deathDate":"","crematoriumName":"C.M.H.O. SPL. REGISTRATION","deceasedSex":"MALE","crematoriumCode":"","fatherName":"LATE NARAYAN CH.DAS","regnNo":"","deathSite":"M.C.HOSPITAL. KOL"},{"deceasedName":"PRASANTA BILUI","yearOfregistration":"2016","dateOfRegistration":"","deathRegnNo":"3647","deathDate":"","crematoriumName":"C.M.H.O. SPL. REGISTRATION","deceasedSex":"MALE","crematoriumCode":"","fatherName":"LATE NANDA LAL BILUI","regnNo":"","deathSite":"THE CALCUTTA MEDICAL RESEARCH INSTITUTE, KOLKATA-27"},{"deceasedName":"SAMBHUNATH CHAKRABORTY","yearOfregistration":"2016","dateOfRegistration":"","deathRegnNo":"2493","deathDate":"","crematoriumName":"N.E.C.(T)","deceasedSex":"MALE","crematoriumCode":"","fatherName":"LATE PIYARILAL CHAKRABORTY","regnNo":"","deathSite":""},{"deceasedName":"MINTU SINGH","yearOfregistration":"2016","dateOfRegistration":"","deathRegnNo":"668","deathDate":"","crematoriumName":"GARIA B.G.(T)","deceasedSex":"MALE","crematoriumCode":"","fatherName":"LT. MOHAN SINGH","regnNo":"","deathSite":""},{"deceasedName":"RINA BANERJEE","yearOfregistration":"2016","dateOfRegistration":"","deathRegnNo":"3443","deathDate":"","crematoriumName":"M.G.E.C.(T)","deceasedSex":"FEMALE","crematoriumCode":"","fatherName":"N/A","regnNo":"","deathSite":""},{"deceasedName":"RAMENDRA NATH ROY","yearOfregistration":"2016","dateOfRegistration":"","deathRegnNo":"3457","deathDate":"","crematoriumName":"M.G.E.C.(T)","deceasedSex":"MALE","crematoriumCode":"","fatherName":"LATE MANMATHA NATH ROY","regnNo":"","deathSite":""},{"deceasedName":"RANJIT KUMAR BISWAS","yearOfregistration":"2016","dateOfRegistration":"","deathRegnNo":"2508","deathDate":"","crematoriumName":"N.E.C.(T)","deceasedSex":"MALE","crematoriumCode":"","fatherName":"S/O.LATE. NAGENDRA NATH BISWAS","regnNo":"","deathSite":""},{"deceasedName":"PHANIBHUSHAN MANDAL","yearOfregistration":"2016","dateOfRegistration":"","deathRegnNo":"3467","deathDate":"","crematoriumName":"M.G.E.C.(T)","deceasedSex":"MALE","crematoriumCode":"","fatherName":"LATE SUDHANA MANDAL","regnNo":"","deathSite":"S S K M HOSPITAL. KOLKATA"},{"deceasedName":"JALADHI NATH ROY","yearOfregistration":"2016","dateOfRegistration":"","deathRegnNo":"3469","deathDate":"","crematoriumName":"M.G.E.C.(T)","deceasedSex":"MALE","crematoriumCode":"","fatherName":"LATE JOGENDRA NATH ROY","regnNo":"","deathSite":""},{"deceasedName":"CHARUBALA SAHA","yearOfregistration":"2016","dateOfRegistration":"","deathRegnNo":"3470","deathDate":"","crematoriumName":"M.G.E.C.(T)","deceasedSex":"FEMALE","crematoriumCode":"","fatherName":"N/A","regnNo":"","deathSite":"M R BANGUR HOSPITAL,KOLKATA 700033"},{"deceasedName":"DEBUBALA GHOSH","yearOfregistration":"2016","dateOfRegistration":"","deathRegnNo":"3476","deathDate":"","crematoriumName":"M.G.E.C.(T)","deceasedSex":"FEMALE","crematoriumCode":"","fatherName":"N/A","regnNo":"","deathSite":""},{"deceasedName":"DULAL DEBNATH","yearOfregistration":"2016","dateOfRegistration":"","deathRegnNo":"521","deathDate":"","crematoriumName":"C.B.G.(T)","deceasedSex":"MALE","crematoriumCode":"","fatherName":"LATE ANIL DEBNATH","regnNo":"","deathSite":"MEDICAL COLLEGE AND HOSPITAL,KOLKATA 73"},{"deceasedName":"B/O TRISHNA  DEY","yearOfregistration":"2016","dateOfRegistration":"","deathRegnNo":"209","deathDate":"","crematoriumName":"TOPSIA HINDU B.G.(T)","deceasedSex":"MALE","crematoriumCode":"","fatherName":"PROBAL DEEP DAS","regnNo":"","deathSite":"RAMKRISHNA SARADA MISSION MATRI BHAVAN"},{"deceasedName":"BASANT LAL","yearOfregistration":"2016","dateOfRegistration":"","deathRegnNo":"3208","deathDate":"","crematoriumName":"C.M.H.O. SPL. REGISTRATION","deceasedSex":"MALE","crematoriumCode":"","fatherName":"LATE KALIDIN JAISWARA","regnNo":"","deathSite":"COMMAND HOSPITAL (E.C.) KOL"},{"deceasedName":"PALASH PATRA","yearOfregistration":"2016","dateOfRegistration":"","deathRegnNo":"4134","deathDate":"","crematoriumName":"C.M.H.O. SPL. REGISTRATION","deceasedSex":"MALE","crematoriumCode":"","fatherName":"BISWANATH PATRA","regnNo":"","deathSite":"S S K M HOSPITAL. KOLKATA"},{"deceasedName":"BISHAKHA SAHA (SHAW)","yearOfregistration":"2016","dateOfRegistration":"","deathRegnNo":"2491","deathDate":"","crematoriumName":"N.E.C.(T)","deceasedSex":"FEMALE","crematoriumCode":"","fatherName":"N/M","regnNo":"","deathSite":"RECOVERY NURSING HOME PVT. LTD"},{"deceasedName":"LAKHI NARAYAN MANDAL","yearOfregistration":"2016","dateOfRegistration":"","deathRegnNo":"2492","deathDate":"","crematoriumName":"N.E.C.(T)","deceasedSex":"MALE","crematoriumCode":"","fatherName":"LATE GOBARDHAN MANDAL","regnNo":"","deathSite":""},{"deceasedName":"SIMA DEY","yearOfregistration":"2016","dateOfRegistration":"","deathRegnNo":"11916","deathDate":"","crematoriumName":"C.M.H.O. SPL. REGISTRATION","deceasedSex":"FEMALE","crematoriumCode":"","fatherName":"N/M","regnNo":"","deathSite":"R G KAR MEDICAL COLLEGE AND HOSPITAL KOL"},{"deceasedName":"MAYA CHATTERJEE","yearOfregistration":"2016","dateOfRegistration":"","deathRegnNo":"12493","deathDate":"","crematoriumName":"C.M.H.O. SPL. REGISTRATION","deceasedSex":"FEMALE","crematoriumCode":"","fatherName":"N/M","regnNo":"","deathSite":"B.R.SINGH HOSPITAL,KOLKATA"},{"deceasedName":"GAMA SAH","yearOfregistration":"2016","dateOfRegistration":"","deathRegnNo":"8036","deathDate":"","crematoriumName":"C.M.H.O. SPL. REGISTRATION","deceasedSex":"MALE","crematoriumCode":"","fatherName":"LATE SONE LAL SAH","regnNo":"","deathSite":"SUNFLOWER  NURSING  HOME"},{"deceasedName":"SABITRI HALDER","yearOfregistration":"2016","dateOfRegistration":"","deathRegnNo":"9262","deathDate":"","crematoriumName":"C.M.H.O. SPL. REGISTRATION","deceasedSex":"FEMALE","crematoriumCode":"","fatherName":"N/M","regnNo":"","deathSite":"R G KAR MEDICAL COLLEGE AND HOSPITAL KOL"},{"deceasedName":"JAMUNA DAS","yearOfregistration":"2016","dateOfRegistration":"","deathRegnNo":"11099","deathDate":"","crematoriumName":"C.M.H.O. SPL. REGISTRATION","deceasedSex":"FEMALE","crematoriumCode":"","fatherName":"N.M","regnNo":"","deathSite":"R G KAR MEDICAL COLLEGE AND HOSPITAL KOL"},{"deceasedName":"RABINDRANATH GHOSH","yearOfregistration":"2016","dateOfRegistration":"","deathRegnNo":"6955","deathDate":"","crematoriumName":"C.M.H.O. SPL. REGISTRATION","deceasedSex":"MALE","crematoriumCode":"","fatherName":"LATE JIBAN KRISHNA GHOSH","regnNo":"","deathSite":"R G KAR MEDICAL COLLEGE AND HOSPITAL KOL"},{"deceasedName":"NARESH KUMAR","yearOfregistration":"2016","dateOfRegistration":"","deathRegnNo":"7527","deathDate":"","crematoriumName":"C.M.H.O. SPL. REGISTRATION","deceasedSex":"MALE","crematoriumCode":"","fatherName":"LOOTAN YADAV","regnNo":"","deathSite":"MEDICA SUPERSPECIALTY HOSPITAL.KOL 99"},{"deceasedName":"KAMALA KANTA MONDAL","yearOfregistration":"2016","dateOfRegistration":"","deathRegnNo":"10977","deathDate":"","crematoriumName":"C.M.H.O. SPL. REGISTRATION","deceasedSex":"MALE","crematoriumCode":"","fatherName":"GOUR CH MONDAL","regnNo":"","deathSite":"S S K M HOSPITAL. KOLKATA"},{"deceasedName":"TUSAR CHAKRABORTY","yearOfregistration":"2016","dateOfRegistration":"","deathRegnNo":"11490","deathDate":"","crematoriumName":"C.M.H.O. SPL. REGISTRATION","deceasedSex":"MALE","crematoriumCode":"","fatherName":"LATE KAMAKHA CHARAN CHAKRABORTY","regnNo":"","deathSite":"S S K M HOSPITAL. KOLKATA"},{"deceasedName":"SARBANI SEN","yearOfregistration":"2016","dateOfRegistration":"","deathRegnNo":"6769","deathDate":"","crematoriumName":"C.M.H.O. SPL. REGISTRATION","deceasedSex":"FEMALE","crematoriumCode":"","fatherName":"N.M","regnNo":"","deathSite":"PEERLESS HOSPITEX HOSPITAL AND RESEARCH CENTER LIMITED, KOLKATA-94."},{"deceasedName":"WADI AYUB","yearOfregistration":"2016","dateOfRegistration":"","deathRegnNo":"6993","deathDate":"","crematoriumName":"C.M.H.O. SPL. REGISTRATION","deceasedSex":"MALE","crematoriumCode":"","fatherName":"LATE FAKIR MOHAMMAD SK","regnNo":"","deathSite":""},{"deceasedName":"SK AYUB ALI","yearOfregistration":"2016","dateOfRegistration":"","deathRegnNo":"9687","deathDate":"","crematoriumName":"C.M.H.O. SPL. REGISTRATION","deceasedSex":"MALE","crematoriumCode":"","fatherName":"LATE SK DEBIRUDDIN","regnNo":"","deathSite":"M.C.HOSPITAL. KOL"},{"deceasedName":"KANAK PAL","yearOfregistration":"2017","dateOfRegistration":"","deathRegnNo":"2437","deathDate":"","crematoriumName":"C.M.H.O. SPL. REGISTRATION","deceasedSex":"FEMALE","crematoriumCode":"","fatherName":"N/M","regnNo":"","deathSite":"S S K M HOSPITAL. KOLKATA"}]}